Workbook

Sheet Resumo
A1: fatura | B1: ord | C1: item | D1: valor
A2: 269308 | B2: 1 | C2: LEVA 1
A3: 269308 | B3: 2 | C3: (+) Notas fiscais recolhidas | D3: 414653.70
A4: 269308 | B4: 3 | C4: (-) Créditos de estorno | D4: -1468.57
A5: 269308 | B5: 4 | C5: (=) Pagamento no vencimento | D5: 413185.13
A6: 269308 | B6: 5 | C6: LEVA 2
A7: 269308 | B7: 6 | C7: (+) Abastecimento cancelado | D7: 331.89
A8: 269308 | B8: 7 | C8: (+) Sem nota fiscal | D8: 29660.05
A9: 269308 | B9: 8 | C9: (=) Saldo a pagar | D9: 29991.94
A10: 269308 | B10: 9 | C10: TOTAL DA FATURA (conferência) | D10: 443177.07

Sheet Contabilidade
A1: cnpj_cliente | B1: garagem | C1: matricula_veiculo | D1: placa | E1: natureza_bluefllet | F1: fatura_atual | G1: data_transacao | H1: id_transacao_atual | I1: numero_nota_fiscal | J1: nome_posto | K1: cnpj_posto | L1: cnpj_filial_nfe | M1: valor_item_liquido | N1: tipo_lancamento | O1: id_referencia_original | P1: fatura_origem_referencia | Q1: data_original_referencia | R1: valor_cobrado_na_epoca | S1: status_fiscal | T1: nfe_tipo_operacao | U1: nfe_data_emissao | V1: nfe_valor_nota | W1: chave_nfe | X1: categoria_relatorio | Y1: titulo_data_geracao | Z1: titulo_data_vencimento | AA1: titulo_valor_total | AB1: fatura_credito_retorno | AC1: data_credito_retorno | AD1: tem_credito_gerado | AE1: chave_nfe_texto
A2: 90739624000118 | B2: GRITSCH - CGB | D2: SFL2F19 | E2: COMBUSTÍVEL | F2: 269308 | G2: 2026-08-01 14:03:55.000 -0300 | H2: 25041264 | J2: POSTO SAO JOSE 1 | K2: 4903852000140 | M2: -285.67 | N2: ESTORNO (CRÉDITO) | O2: 24567446 | P2: 267384 | Q2: 2026-08-01 14:03:55.000 -0300 | R2: 285.67 | S2: CRÉDITO / ESTORNO | X2: 4. Crédito de estorno (desconto) | Y2: 2026-08-15 00:00:00.000 -0300 | Z2: 2026-08-26 00:00:00.000 -0300 | AA2: 443177.07 | AD2: false
A3: 90739624000118 | B3: GRITSCH - POA | D3: UBR9A92 | E3: COMBUSTÍVEL | F3: 269308 | G3: 2026-07-28 18:26:06.000 -0300 | H3: 25041210 | J3: SIM REDE - ALEGRETE - 019877 - CENTRO RS | K3: 7473735019877 | M3: -251.86 | N3: ESTORNO (CRÉDITO) | O3: 24375893 | P3: 267384 | Q3: 2026-07-28 18:26:06.000 -0300 | R3: 251.86 | S3: CRÉDITO / ESTORNO | X3: 4. Crédito de estorno (desconto) | Y3: 2026-08-15 00:00:00.000 -0300 | Z3: 2026-08-26 00:00:00.000 -0300 | AA3: 443177.07 | AD3: false
A4: 90739624000118 | B4: GRITSCH - PET | D4: UBN9E24 | E4: COMBUSTÍVEL | F4: 269308 | G4: 2026-07-31 08:16:17.000 -0300 | H4: 25030298 | J4: SIM REDE - PELOTAS FERNANDO OSORIO 0093-08 - CENTRO RS | K4: 7473735009308 | M4: -141.68 | N4: ESTORNO (CRÉDITO) | O4: 24502758 | P4: 267384 | Q4: 2026-07-31 08:16:17.000 -0300 | R4: 141.68 | S4: CRÉDITO / ESTORNO | X4: 4. Crédito de estorno (desconto) | Y4: 2026-08-15 00:00:00.000 -0300 | Z4: 2026-08-26 00:00:00.000 -0300 | AA4: 443177.07 | AD4: false
A5: 90739624000118 | B5: GRITSCH - RVD | C5: 22475 | D5: SDU9F98 | E5: COMBUSTÍVEL | F5: 269308 | G5: 2026-08-07 10:14:51.000 -0300 | H5: 24861044 | J5: POSTO ALDO JATAI INDUSTRIAL - REDE ALDO | K5: 2651099000117 | M5: -331.89 | N5: ESTORNO (CRÉDITO) | O5: 24860705 | P5: 269308 | Q5: 2026-08-07 10:14:51.000 -0300 | R5: 331.89 | S5: CRÉDITO / ESTORNO | X5: 4. Crédito de estorno (desconto) | Y5: 2026-08-15 00:00:00.000 -0300 | Z5: 2026-08-26 00:00:00.000 -0300 | AA5: 443177.07 | AD5: false
A6: 90739624000118 | B6: GRITSCH - GOI | D6: TBE5I66 | E6: COMBUSTÍVEL | F6: 269308 | G6: 2026-08-03 14:18:13.000 -0300 | H6: 25027473 | J6: POSTO SAO JUDAS TADEU - REDE Z+Z (RODOVIA) | K6: 13759928000104 | M6: -231.7 | N6: ESTORNO (CRÉDITO) | O6: 24661956 | P6: 267384 | Q6: 2026-08-03 14:18:13.000 -0300 | R6: 231.70 | S6: CRÉDITO / ESTORNO | X6: 4. Crédito de estorno (desconto) | Y6: 2026-08-15 00:00:00.000 -0300 | Z6: 2026-08-26 00:00:00.000 -0300 | AA6: 443177.07 | AD6: false
A7: 90739624000118 | B7: GRITSCH - GOI | D7: TBE5I66 | E7: COMBUSTÍVEL | F7: 269308 | G7: 2026-07-30 15:13:04.000 -0300 | H7: 25029954 | J7: POSTO SAO JUDAS TADEU - REDE Z+Z (RODOVIA) | K7: 13759928000104 | M7: -225.77 | N7: ESTORNO (CRÉDITO) | O7: 24469630 | P7: 267384 | Q7: 2026-07-30 15:13:04.000 -0300 | R7: 225.77 | S7: CRÉDITO / ESTORNO | X7: 4. Crédito de estorno (desconto) | Y7: 2026-08-15 00:00:00.000 -0300 | Z7: 2026-08-26 00:00:00.000 -0300 | AA7: 443177.07 | AD7: false
A8: 90739624000118 | B8: GRITSCH - MATRIZ | D8: SFH7D75 | E8: COMBUSTÍVEL | F8: 269308 | G8: 2026-08-11 20:32:34.000 -0300 | H8: 25063040 | I8: 29106 | J8: POSTO 2 IRMAOS | K8: 76493295000147 | L8: 9576274000106 | M8: 252.02 | N8: ABASTECIMENTO (DÉBITO) | S8: NFE VINCULADA | T8: I | U8: 2026-08-10 21:00:00.000 -0300 | V8: 252.02 | W8: 4.1260876e+43 | X8: 1. Com nota fiscal recolhida | Y8: 2026-08-15 00:00:00.000 -0300 | Z8: 2026-08-26 00:00:00.000 -0300 | AA8: 443177.07 | AD8: false | AE8: '41260876493295000147550020000291061002782187
A9: 90739624000118 | B9: GRITSCH - RVD | D9: TBK1J24 | E9: COMBUSTÍVEL | F9: 269308 | G9: 2026-08-11 20:16:50.000 -0300 | H9: 25062781 | I9: 5325 | J9: REDE MONTE CARLO - POSTO SAO JOSE | K9: 42733072000198 | L9: 90739624000380 | M9: 283.6 | N9: ABASTECIMENTO (DÉBITO) | S9: NFE VINCULADA | T9: I | U9: 2026-08-11 21:00:00.000 -0300 | V9: 283.60 | W9: 3.5260843e+43 | X9: 1. Com nota fiscal recolhida | Y9: 2026-08-15 00:00:00.000 -0300 | Z9: 2026-08-26 00:00:00.000 -0300 | AA9: 443177.07 | AD9: false | AE9: '35260842733072000198550080000053251524484620
A10: 90739624000118 | B10: GRITSCH - GOI | D10: UAV5J73 | E10: COMBUSTÍVEL | F10: 269308 | G10: 2026-08-11 19:42:40.000 -0300 | H10: 25062357 | I10: 38315 | J10: AUTO POSTO CIDADE - PORANGATU | K10: 33360405000190 | L10: 90739624001947 | M10: 220.77 | N10: ABASTECIMENTO (DÉBITO) | S10: NFE VINCULADA | T10: I | U10: 2026-08-10 21:00:00.000 -0300 | V10: 220.77 | W10: 5.2260833e+43 | X10: 1. Com nota fiscal recolhida | Y10: 2026-08-15 00:00:00.000 -0300 | Z10: 2026-08-26 00:00:00.000 -0300 | AA10: 443177.07 | AD10: false | AE10: '52260833360405000190550020000383151008888133
A11: 90739624000118 | B11: GRITSCH - SAO (PERUS) | D11: UCB6D90 | E11: COMBUSTÍVEL | F11: 269308 | G11: 2026-08-11 19:17:08.000 -0300 | H11: 25061999 | I11: 1052949 | J11: POSTO DO TREVO - REDE GRAAL | K11: 55973291000196 | L11: 90739624000380 | M11: 336.5 | N11: ABASTECIMENTO (DÉBITO) | S11: NFE VINCULADA | T11: I | U11: 2026-08-10 21:00:00.000 -0300 | V11: 336.50 | W11: 3.5260856e+43 | X11: 1. Com nota fiscal recolhida | Y11: 2026-08-15 00:00:00.000 -0300 | Z11: 2026-08-26 00:00:00.000 -0300 | AA11: 443177.07 | AD11: false | AE11: '35260855973291000196550030010529491018448930
A12: 90739624000118 | B12: GRITSCH - CWB (BASE) | D12: UCC8A40 | E12: COMBUSTÍVEL | F12: 269308 | G12: 2026-08-11 19:14:36.000 -0300 | H12: 25061890 | I12: 820855 | J12: GP POSTOS - POSTO SAO JOSE | K12: 79964177000591 | L12: 9576274000106 | M12: 698.82 | N12: ABASTECIMENTO (DÉBITO) | S12: NFE VINCULADA | T12: I | U12: 2026-08-10 21:00:00.000 -0300 | V12: 698.82 | W12: 4.126088e+43 | X12: 1. Com nota fiscal recolhida | Y12: 2026-08-15 00:00:00.000 -0300 | Z12: 2026-08-26 00:00:00.000 -0300 | AA12: 443177.07 | AD12: false | AE12: '41260879964177000591550020008208551011758525
A13: 90739624000118 | B13: GRITSCH - PMW | D13: UAV5J75 | E13: COMBUSTÍVEL | F13: 269308 | G13: 2026-08-11 19:09:13.000 -0300 | H13: 25061863 | I13: 38314 | J13: AUTO POSTO CIDADE - PORANGATU | K13: 33360405000190 | L13: 90739624001947 | M13: 196.89 | N13: ABASTECIMENTO (DÉBITO) | S13: NFE VINCULADA | T13: I | U13: 2026-08-10 21:00:00.000 -0300 | V13: 196.89 | W13: 5.2260833e+43 | X13: 1. Com nota fiscal recolhida | Y13: 2026-08-15 00:00:00.000 -0300 | Z13: 2026-08-26 00:00:00.000 -0300 | AA13: 443177.07 | AD13: false | AE13: '52260833360405000190550020000383141008887997
A14: 90739624000118 | B14: GRITSCH - CWB (BASE) | C14: 15984 | D14: BBW0C96 | E14: COMBUSTÍVEL | F14: 269308 | G14: 2026-08-11 18:36:53.000 -0300 | H14: 25061415 | I14: 820852 | J14: GP POSTOS - POSTO SAO JOSE | K14: 79964177000591 | L14: 9576274000106 | M14: 1878.84 | N14: ABASTECIMENTO (DÉBITO) | S14: NFE VINCULADA | T14: I | U14: 2026-08-10 21:00:00.000 -0300 | V14: 1878.84 | W14: 4.126088e+43 | X14: 1. Com nota fiscal recolhida | Y14: 2026-08-15 00:00:00.000 -0300 | Z14: 2026-08-26 00:00:00.000 -0300 | AA14: 443177.07 | AD14: false | AE14: '41260879964177000591550020008208521011758434
A15: 90739624000118 | B15: GRITSCH - CHA | D15: RHT0B69 | E15: COMBUSTÍVEL | F15: 269308 | G15: 2026-08-11 18:33:59.000 -0300 | H15: 25061399 | I15: 4439 | J15: BUFFON 74 | K15: 93489243007471 | L15: 90739624002323 | M15: 475.6 | N15: ABASTECIMENTO (DÉBITO) | S15: NFE VINCULADA | T15: I | U15: 2026-08-10 21:00:00.000 -0300 | V15: 475.60 | W15: 4.3260893e+43 | X15: 1. Com nota fiscal recolhida | Y15: 2026-08-15 00:00:00.000 -0300 | Z15: 2026-08-26 00:00:00.000 -0300 | AA15: 443177.07 | AD15: false | AE15: '43260893489243007471550080000044391522201280
A16: 90739624000118 | B16: GRITSCH - GOI | D16: TBE5I62 | E16: COMBUSTÍVEL | F16: 269308 | G16: 2026-08-11 17:34:10.000 -0300 | H16: 25056047 | I16: 81440 | J16: POSTO 10 GOIANIA | REDE CARRETEIRO | K16: 1272434001002 | L16: 90739624001947 | M16: 260.28 | N16: ABASTECIMENTO (DÉBITO) | S16: NFE VINCULADA | T16: I | U16: 2026-08-10 21:00:00.000 -0300 | V16: 260.28 | W16: 5.2260801e+43 | X16: 1. Com nota fiscal recolhida | Y16: 2026-08-15 00:00:00.000 -0300 | Z16: 2026-08-26 00:00:00.000 -0300 | AA16: 443177.07 | AD16: false | AE16: '52260801272434001002550020000814401274796734
A17: 90739624000118 | B17: GRITSCH - SAO (PERUS) | C17: 26123 | D17: TAS4H20 | E17: COMBUSTÍVEL | F17: 269308 | G17: 2026-08-11 17:25:18.000 -0300 | H17: 25055879 | I17: 374251 | J17: AUTO POSTO LIMOEIRO - PALOMA - REDE GRAAL | K17: 5065447000162 | L17: 90739624000380 | M17: 221.63 | N17: ABASTECIMENTO (DÉBITO) | S17: NFE VINCULADA | T17: I | U17: 2026-08-10 21:00:00.000 -0300 | V17: 221.63 | W17: 3.5260805e+43 | X17: 1. Com nota fiscal recolhida | Y17: 2026-08-15 00:00:00.000 -0300 | Z17: 2026-08-26 00:00:00.000 -0300 | AA17: 443177.07 | AD17: false | AE17: '35260805065447000162550060003742511006200254
A18: 90739624000118 | B18: GRITSCH - RDN | C18: 23395 | D18: SEI5B85 | E18: COMBUSTÍVEL | F18: 269308 | G18: 2026-08-11 17:22:05.000 -0300 | H18: 25055759 | I18: 10286 | J18: REDE DINO - POSTO SERRA DAS ARARAS | K18: 50128357000551 | L18: 90739624001866 | M18: 189.65 | N18: ABASTECIMENTO (DÉBITO) | S18: NFE VINCULADA | T18: I | U18: 2026-08-10 21:00:00.000 -0300 | V18: 189.64 | W18: 5.126085e+43 | X18: 1. Com nota fiscal recolhida | Y18: 2026-08-15 00:00:00.000 -0300 | Z18: 2026-08-26 00:00:00.000 -0300 | AA18: 443177.07 | AD18: false | AE18: '51260850128357000551550050000102861001035117
A19: 90739624000118 | B19: GRITSCH - POA | D19: TAI9A24 | E19: COMBUSTÍVEL | F19: 269308 | G19: 2026-08-11 17:17:58.000 -0300 | H19: 25055716 | I19: 58070 | J19: SIM REDE - ALEGRETE - 019877 - CENTRO RS | K19: 7473735019877 | L19: 90739624002323 | M19: 255.16 | N19: ABASTECIMENTO (DÉBITO) | S19: NFE VINCULADA | T19: I | U19: 2026-08-10 21:00:00.000 -0300 | V19: 255.16 | W19: 4.3260807e+43 | X19: 1. Com nota fiscal recolhida | Y19: 2026-08-15 00:00:00.000 -0300 | Z19: 2026-08-26 00:00:00.000 -0300 | AA19: 443177.07 | AD19: false | AE19: '43260807473735019877550080000580701009183062
A20: 90739624000118 | B20: GRITSCH - CWB (BASE) | D20: SFM3H28 | E20: COMBUSTÍVEL | F20: 269308 | G20: 2026-08-11 17:13:35.000 -0300 | H20: 25055585 | I20: 29103 | J20: POSTO 2 IRMAOS | K20: 76493295000147 | L20: 9576274000106 | M20: 620.71 | N20: ABASTECIMENTO (DÉBITO) | S20: NFE VINCULADA | T20: I | U20: 2026-08-10 21:00:00.000 -0300 | V20: 620.71 | W20: 4.1260876e+43 | X20: 1. Com nota fiscal recolhida | Y20: 2026-08-15 00:00:00.000 -0300 | Z20: 2026-08-26 00:00:00.000 -0300 | AA20: 443177.07 | AD20: false | AE20: '41260876493295000147550020000291031002781545
A21: 90739624000118 | B21: GRITSCH - GOI | D21: TBQ1G08 | E21: ARLA | F21: 269308 | G21: 2026-08-11 17:12:26.000 -0300 | H21: 25055573 | I21: 90596 | J21: POSTO 6 RIANAPOLIS | REDE CARRETEIRO | K21: 1272434000618 | L21: 90739624001947 | M21: 59.8 | N21: ABASTECIMENTO (DÉBITO) | S21: NFE VINCULADA | T21: I | U21: 2026-08-10 21:00:00.000 -0300 | V21: 59.80 | W21: 5.2260801e+43 | X21: 1. Com nota fiscal recolhida | Y21: 2026-08-15 00:00:00.000 -0300 | Z21: 2026-08-26 00:00:00.000 -0300 | AA21: 443177.07 | AD21: false | AE21: '52260801272434000618550030000905961193214770
A22: 90739624000118 | B22: GRITSCH - CSC | D22: SES0D47 | E22: COMBUSTÍVEL | F22: 269308 | G22: 2026-08-11 17:09:49.000 -0300 | H22: 25055555 | I22: 163227 | J22: POSTO NOVO FOXX - REDE ESTRADA | K22: 2763612000161 | L22: 90739624003133 | M22: 660.15 | N22: ABASTECIMENTO (DÉBITO) | S22: NFE VINCULADA | T22: I | U22: 2026-08-10 21:00:00.000 -0300 | V22: 660.15 | W22: 4.1260803e+43 | X22: 1. Com nota fiscal recolhida | Y22: 2026-08-15 00:00:00.000 -0300 | Z22: 2026-08-26 00:00:00.000 -0300 | AA22: 443177.07 | AD22: false | AE22: '41260802763612000161550020001632271664883173
A23: 90739624000118 | B23: GRITSCH - PMW | D23: TAR2F19 | E23: COMBUSTÍVEL | F23: 269308 | G23: 2026-08-11 17:05:49.000 -0300 | H23: 25055420 | I23: 99280 | J23: RODOPOSTO | K23: 4219621000111 | L23: 90739624000118 | M23: 305.06 | N23: ABASTECIMENTO (DÉBITO) | S23: NFE VINCULADA | T23: I | U23: 2026-08-11 21:00:00.000 -0300 | V23: 305.06 | W23: 1.7260804e+43 | X23: 1. Com nota fiscal recolhida | Y23: 2026-08-15 00:00:00.000 -0300 | Z23: 2026-08-26 00:00:00.000 -0300 | AA23: 443177.07 | AD23: false | AE23: '17260804219621000111550010000992801351423972
A24: 90739624000118 | B24: GRITSCH - CTB | C24: 24753 | D24: SFI4A35 | E24: COMBUSTÍVEL | F24: 269308 | G24: 2026-08-11 16:59:05.000 -0300 | H24: 25055367 | I24: 168726 | J24: POSTO CAPITAL | K24: 82156977000248 | L24: 90739624001432 | M24: 234.43 | N24: ABASTECIMENTO (DÉBITO) | S24: NFE VINCULADA | T24: I | U24: 2026-08-10 21:00:00.000 -0300 | V24: 234.43 | W24: 4.2260882e+43 | X24: 1. Com nota fiscal recolhida | Y24: 2026-08-15 00:00:00.000 -0300 | Z24: 2026-08-26 00:00:00.000 -0300 | AA24: 443177.07 | AD24: false | AE24: '42260882156977000248550010001687261220982295
A25: 90739624000118 | B25: GRITSCH - CGB | D25: SFL2F19 | E25: COMBUSTÍVEL | F25: 269308 | G25: 2026-08-11 16:50:56.000 -0300 | H25: 25055190 | I25: 171981 | J25: POSTO JK - COMODORO | REDE AMERICA | K25: 22611652000103 | L25: 90739624001866 | M25: 139.9 | N25: ABASTECIMENTO (DÉBITO) | S25: NFE VINCULADA | T25: I | U25: 2026-08-10 21:00:00.000 -0300 | V25: 139.90 | W25: 5.1260823e+43 | X25: 1. Com nota fiscal recolhida | Y25: 2026-08-15 00:00:00.000 -0300 | Z25: 2026-08-26 00:00:00.000 -0300 | AA25: 443177.07 | AD25: false | AE25: '51260822611652000103550010001719811020410220
A26: 90739624000118 | B26: GRITSCH - SNO | D26: SFD5C40 | E26: COMBUSTÍVEL | F26: 269308 | G26: 2026-08-11 16:39:34.000 -0300 | H26: 25054973 | I26: 342733 | J26: POSTO TREVAO GUARANTA | K26: 17084739000121 | L26: 90739624001866 | M26: 162.36 | N26: ABASTECIMENTO (DÉBITO) | S26: NFE VINCULADA | T26: I | U26: 2026-08-10 21:00:00.000 -0300 | V26: 162.36 | W26: 5.1260817e+43 | X26: 1. Com nota fiscal recolhida | Y26: 2026-08-15 00:00:00.000 -0300 | Z26: 2026-08-26 00:00:00.000 -0300 | AA26: 443177.07 | AD26: false | AE26: '51260817084739000121550010003427331007357872
A27: 90739624000118 | B27: GRITSCH - BLN | D27: RHL3E04 | E27: COMBUSTÍVEL | F27: 269308 | G27: 2026-08-11 16:36:05.000 -0300 | H27: 25054931 | I27: 130148 | J27: POSTO ZANDONA 12 | K27: 83392050000199 | L27: 90739624001432 | M27: 2457.91 | N27: ABASTECIMENTO (DÉBITO) | S27: NFE VINCULADA | T27: I | U27: 2026-08-10 21:00:00.000 -0300 | V27: 2457.91 | W27: 4.2260883e+43 | X27: 1. Com nota fiscal recolhida | Y27: 2026-08-15 00:00:00.000 -0300 | Z27: 2026-08-26 00:00:00.000 -0300 | AA27: 443177.07 | AD27: false | AE27: '42260883392050000199550020001301481111936167
A28: 90739624000118 | B28: GRITSCH - LDB | C28: 24754 | D28: SFI6J89 | E28: COMBUSTÍVEL | F28: 269308 | G28: 2026-08-11 16:34:42.000 -0300 | H28: 25054905 | I28: 10524 | J28: AUTO POSTO BARUK | K28: 33286065000102 | L28: 9576274000106 | M28: 350.27 | N28: ABASTECIMENTO (DÉBITO) | S28: NFE VINCULADA | T28: I | U28: 2026-08-10 21:00:00.000 -0300 | V28: 350.27 | W28: 4.1260833e+43 | X28: 1. Com nota fiscal recolhida | Y28: 2026-08-15 00:00:00.000 -0300 | Z28: 2026-08-26 00:00:00.000 -0300 | AA28: 443177.07 | AD28: false | AE28: '41260833286065000102550040000105241014217700
A29: 90739624000118 | B29: GRITSCH - CSC | C29: 23846 | D29: SEP6E33 | E29: COMBUSTÍVEL | F29: 269308 | G29: 2026-08-11 16:31:43.000 -0300 | H29: 25054777 | I29: 163223 | J29: POSTO NOVO FOXX - REDE ESTRADA | K29: 2763612000161 | L29: 90739624003133 | M29: 219.52 | N29: ABASTECIMENTO (DÉBITO) | S29: NFE VINCULADA | T29: I | U29: 2026-08-10 21:00:00.000 -0300 | V29: 219.52 | W29: 4.1260803e+43 | X29: 1. Com nota fiscal recolhida | Y29: 2026-08-15 00:00:00.000 -0300 | Z29: 2026-08-26 00:00:00.000 -0300 | AA29: 443177.07 | AD29: false | AE29: '41260802763612000161550020001632231469305060
A30: 90739624000118 | B30: GRITSCH - RVD | D30: SFI4A20 | E30: COMBUSTÍVEL | F30: 269308 | G30: 2026-08-11 16:31:41.000 -0300 | H30: 25054776 | I30: 6749 | J30: POSTO CPN - BR | K30: 23891404000118 | L30: 90739624001866 | M30: 230.47 | N30: ABASTECIMENTO (DÉBITO) | S30: NFE VINCULADA | T30: I | U30: 2026-08-13 21:00:00.000 -0300 | V30: 230.47 | W30: 5.1260824e+43 | X30: 1. Com nota fiscal recolhida | Y30: 2026-08-15 00:00:00.000 -0300 | Z30: 2026-08-26 00:00:00.000 -0300 | AA30: 443177.07 | AD30: false | AE30: '51260823891404000118551010000067491089991170
A31: 90739624000118 | B31: GRITSCH - CGR | C31: 26010 | D31: TAP3G60 | E31: COMBUSTÍVEL | F31: 269308 | G31: 2026-08-11 16:31:11.000 -0300 | H31: 25054770 | I31: 16711 | J31: POSTO SAN MARTIN | K31: 1550726000160 | L31: 90739624001190 | M31: 372.14 | N31: ABASTECIMENTO (DÉBITO) | S31: NFE VINCULADA | T31: I | U31: 2026-08-12 21:00:00.000 -0300 | V31: 372.14 | W31: 5.0260802e+43 | X31: 1. Com nota fiscal recolhida | Y31: 2026-08-15 00:00:00.000 -0300 | Z31: 2026-08-26 00:00:00.000 -0300 | AA31: 443177.07 | AD31: false | AE31: '50260801550726000160550030000167111130728365
A32: 90739624000118 | B32: GRITSCH - MGA | D32: SFD3E82 | E32: COMBUSTÍVEL | F32: 269308 | G32: 2026-08-11 16:22:55.000 -0300 | H32: 25054603 | I32: 41275 | J32: COCAMAR - MARINGA | REDE COCAMAR MARINGA - PR | K32: 30429333000282 | L32: 9576274000106 | M32: 168.71 | N32: ABASTECIMENTO (DÉBITO) | S32: NFE VINCULADA | T32: I | U32: 2026-08-10 21:00:00.000 -0300 | V32: 168.71 | W32: 4.126083e+43 | X32: 1. Com nota fiscal recolhida | Y32: 2026-08-15 00:00:00.000 -0300 | Z32: 2026-08-26 00:00:00.000 -0300 | AA32: 443177.07 | AD32: false | AE32: '41260830429333000282550110000412751005184719
A33: 90739624000118 | B33: GRITSCH - CTB | D33: TBQ1G07 | E33: ARLA | F33: 269308 | G33: 2026-08-11 16:06:38.000 -0300 | H33: 25054240 | I33: 168722 | J33: POSTO CAPITAL | K33: 82156977000248 | L33: 90739624001432 | M33: 26.32 | N33: ABASTECIMENTO (DÉBITO) | S33: NFE VINCULADA | T33: I | U33: 2026-08-10 21:00:00.000 -0300 | V33: 26.32 | W33: 4.2260882e+43 | X33: 1. Com nota fiscal recolhida | Y33: 2026-08-15 00:00:00.000 -0300 | Z33: 2026-08-26 00:00:00.000 -0300 | AA33: 443177.07 | AD33: false | AE33: '42260882156977000248550010001687221951919602
A34: 90739624000118 | B34: GRITSCH - CTB | D34: TBQ1G07 | E34: COMBUSTÍVEL | F34: 269308 | G34: 2026-08-11 16:05:33.000 -0300 | H34: 25054226 | I34: 168721 | J34: POSTO CAPITAL | K34: 82156977000248 | L34: 90739624001432 | M34: 221.6 | N34: ABASTECIMENTO (DÉBITO) | S34: NFE VINCULADA | T34: I | U34: 2026-08-10 21:00:00.000 -0300 | V34: 221.60 | W34: 4.2260882e+43 | X34: 1. Com nota fiscal recolhida | Y34: 2026-08-15 00:00:00.000 -0300 | Z34: 2026-08-26 00:00:00.000 -0300 | AA34: 443177.07 | AD34: false | AE34: '42260882156977000248550010001687211575440027
A35: 90739624000118 | B35: GRITSCH - CWB (BASE) | D35: SEL7G42 | E35: COMBUSTÍVEL | F35: 269308 | G35: 2026-08-11 16:04:53.000 -0300 | H35: 25054214 | I35: 389635 | J35: POSTO BARAO MATRIZ|| REDE BARAO | K35: 75176859000155 | L35: 9576274000106 | M35: 303.44 | N35: ABASTECIMENTO (DÉBITO) | S35: NFE VINCULADA | T35: I | U35: 2026-08-10 21:00:00.000 -0300 | V35: 303.44 | W35: 4.1260875e+43 | X35: 1. Com nota fiscal recolhida | Y35: 2026-08-15 00:00:00.000 -0300 | Z35: 2026-08-26 00:00:00.000 -0300 | AA35: 443177.07 | AD35: false | AE35: '41260875176859000155550020003896351760533255
A36: 90739624000118 | B36: GRITSCH - SNO | D36: SFN1H25 | E36: COMBUSTÍVEL | F36: 269308 | G36: 2026-08-11 16:02:33.000 -0300 | H36: 25054174 | I36: 74996 | J36: POSTO CASAGRANDA | K36: 1594553000182 | L36: 90739624001866 | M36: 61.05 | N36: ABASTECIMENTO (DÉBITO) | S36: NFE VINCULADA | T36: I | U36: 2026-08-10 21:00:00.000 -0300 | V36: 61.05 | W36: 5.1260802e+43 | X36: 1. Com nota fiscal recolhida | Y36: 2026-08-15 00:00:00.000 -0300 | Z36: 2026-08-26 00:00:00.000 -0300 | AA36: 443177.07 | AD36: false | AE36: '51260801594553000182550100000749961010486291
A37: 90739624000118 | B37: GRITSCH - CSC | D37: RHP7C51 | E37: COMBUSTÍVEL | F37: 269308 | G37: 2026-08-11 16:00:25.000 -0300 | H37: 25054149 | I37: 163217 | J37: POSTO NOVO FOXX - REDE ESTRADA | K37: 2763612000161 | L37: 90739624003133 | M37: 416.68 | N37: ABASTECIMENTO (DÉBITO) | S37: NFE VINCULADA | T37: I | U37: 2026-08-10 21:00:00.000 -0300 | V37: 416.68 | W37: 4.1260803e+43 | X37: 1. Com nota fiscal recolhida | Y37: 2026-08-15 00:00:00.000 -0300 | Z37: 2026-08-26 00:00:00.000 -0300 | AA37: 443177.07 | AD37: false | AE37: '41260802763612000161550020001632171858968259
A38: 90739624000118 | B38: GRITSCH - CTB | C38: 26121 | D38: TAS4H11 | E38: COMBUSTÍVEL | F38: 269308 | G38: 2026-08-11 15:57:50.000 -0300 | H38: 25054114 | I38: 168719 | J38: POSTO CAPITAL | K38: 82156977000248 | L38: 90739624001432 | M38: 232.82 | N38: ABASTECIMENTO (DÉBITO) | S38: NFE VINCULADA | T38: I | U38: 2026-08-10 21:00:00.000 -0300 | V38: 232.82 | W38: 4.2260882e+43 | X38: 1. Com nota fiscal recolhida | Y38: 2026-08-15 00:00:00.000 -0300 | Z38: 2026-08-26 00:00:00.000 -0300 | AA38: 443177.07 | AD38: false | AE38: '42260882156977000248550010001687191881791585
A39: 90739624000118 | B39: GRITSCH - CSC | C39: 25076 | D39: SFM3H46 | E39: COMBUSTÍVEL | F39: 269308 | G39: 2026-08-11 15:49:14.000 -0300 | H39: 25053900 | I39: 163214 | J39: POSTO NOVO FOXX - REDE ESTRADA | K39: 2763612000161 | L39: 90739624003133 | M39: 224.22 | N39: ABASTECIMENTO (DÉBITO) | S39: NFE VINCULADA | T39: I | U39: 2026-08-10 21:00:00.000 -0300 | V39: 224.22 | W39: 4.1260803e+43 | X39: 1. Com nota fiscal recolhida | Y39: 2026-08-15 00:00:00.000 -0300 | Z39: 2026-08-26 00:00:00.000 -0300 | AA39: 443177.07 | AD39: false | AE39: '41260802763612000161550020001632141373894715
A40: 90739624000118 | B40: GRITSCH - GOI | D40: SFD5C36 | E40: COMBUSTÍVEL | F40: 269308 | G40: 2026-08-11 15:48:24.000 -0300 | H40: 25053865 | I40: 81438 | J40: POSTO 10 GOIANIA | REDE CARRETEIRO | K40: 1272434001002 | L40: 90739624001947 | M40: 341.1 | N40: ABASTECIMENTO (DÉBITO) | S40: NFE VINCULADA | T40: I | U40: 2026-08-10 21:00:00.000 -0300 | V40: 341.10 | W40: 5.2260801e+43 | X40: 1. Com nota fiscal recolhida | Y40: 2026-08-15 00:00:00.000 -0300 | Z40: 2026-08-26 00:00:00.000 -0300 | AA40: 443177.07 | AD40: false | AE40: '52260801272434001002550020000814381308342643
A41: 90739624000118 | B41: GRITSCH - CTB | C41: 23397 | D41: SEJ1H97 | E41: COMBUSTÍVEL | F41: 269308 | G41: 2026-08-11 15:46:55.000 -0300 | H41: 25053852 | I41: 168717 | J41: POSTO CAPITAL | K41: 82156977000248 | L41: 90739624001432 | M41: 322.03 | N41: ABASTECIMENTO (DÉBITO) | S41: NFE VINCULADA | T41: I | U41: 2026-08-10 21:00:00.000 -0300 | V41: 322.03 | W41: 4.2260882e+43 | X41: 1. Com nota fiscal recolhida | Y41: 2026-08-15 00:00:00.000 -0300 | Z41: 2026-08-26 00:00:00.000 -0300 | AA41: 443177.07 | AD41: false | AE41: '42260882156977000248550010001687171213692180
A42: 90739624000118 | B42: GRITSCH - SAO (PERUS) | D42: UCB6D90 | E42: COMBUSTÍVEL | F42: 269308 | G42: 2026-08-11 15:46:09.000 -0300 | H42: 25053843 | I42: 23369 | J42: POSTO GRAAL 81 | REDE GRAAL | K42: 46472822000176 | L42: 90739624000380 | M42: 583.31 | N42: ABASTECIMENTO (DÉBITO) | S42: NFE VINCULADA | T42: I | U42: 2026-08-12 21:00:00.000 -0300 | V42: 583.31 | W42: 3.5260846e+43 | X42: 1. Com nota fiscal recolhida | Y42: 2026-08-15 00:00:00.000 -0300 | Z42: 2026-08-26 00:00:00.000 -0300 | AA42: 443177.07 | AD42: false | AE42: '35260846472822000176550010000233691003157909
A43: 90739624000118 | B43: GRITSCH - CTB | C43: 22016 | D43: SDS3F58 | E43: ARLA | F43: 269308 | G43: 2026-08-11 15:38:29.000 -0300 | H43: 25053685 | I43: 168716 | J43: POSTO CAPITAL | K43: 82156977000248 | L43: 90739624001432 | M43: 39.48 | N43: ABASTECIMENTO (DÉBITO) | S43: NFE VINCULADA | T43: I | U43: 2026-08-10 21:00:00.000 -0300 | V43: 39.48 | W43: 4.2260882e+43 | X43: 1. Com nota fiscal recolhida | Y43: 2026-08-15 00:00:00.000 -0300 | Z43: 2026-08-26 00:00:00.000 -0300 | AA43: 443177.07 | AD43: false | AE43: '42260882156977000248550010001687161410323210
A44: 90739624000118 | B44: GRITSCH - CTB | C44: 22016 | D44: SDS3F58 | E44: COMBUSTÍVEL | F44: 269308 | G44: 2026-08-11 15:36:40.000 -0300 | H44: 25053662 | I44: 168714 | J44: POSTO CAPITAL | K44: 82156977000248 | L44: 90739624001432 | M44: 294.27 | N44: ABASTECIMENTO (DÉBITO) | S44: NFE VINCULADA | T44: I | U44: 2026-08-10 21:00:00.000 -0300 | V44: 294.27 | W44: 4.2260882e+43 | X44: 1. Com nota fiscal recolhida | Y44: 2026-08-15 00:00:00.000 -0300 | Z44: 2026-08-26 00:00:00.000 -0300 | AA44: 443177.07 | AD44: false | AE44: '42260882156977000248550010001687141659026456
A45: 90739624000118 | B45: GRITSCH - GOI | D45: TAI9A19 | E45: COMBUSTÍVEL | F45: 269308 | G45: 2026-08-11 15:34:32.000 -0300 | H45: 25053634 | I45: 113417 | J45: POSTO CALIFORNIA - PASADENA | K45: 47377960000139 | L45: 90739624001947 | M45: 210.91 | N45: ABASTECIMENTO (DÉBITO) | S45: NFE VINCULADA | T45: I | U45: 2026-08-10 21:00:00.000 -0300 | V45: 210.90 | W45: 5.2260847e+43 | X45: 1. Com nota fiscal recolhida | Y45: 2026-08-15 00:00:00.000 -0300 | Z45: 2026-08-26 00:00:00.000 -0300 | AA45: 443177.07 | AD45: false | AE45: '52260847377960000139550010001134171584734398
A46: 90739624000118 | B46: GRITSCH - POA | D46: UBR9A97 | E46: COMBUSTÍVEL | F46: 269308 | G46: 2026-08-11 15:33:34.000 -0300 | H46: 25053621 | J46: SIM REDE - URUGUAIANA BR 290 0152-94 - CENTRO RS | K46: 7473735015294 | M46: 268.65 | N46: ABASTECIMENTO (DÉBITO) | S46: PENDENTE DE NOTA | X46: 3. Sem nota fiscal | Y46: 2026-08-15 00:00:00.000 -0300 | Z46: 2026-08-26 00:00:00.000 -0300 | AA46: 443177.07 | AD46: false
A47: 90739624000118 | B47: GRITSCH - CWB (BASE) | D47: RHS8D41 | E47: COMBUSTÍVEL | F47: 269308 | G47: 2026-08-11 15:25:17.000 -0300 | H47: 25053293 | I47: 2544 | J47: POSTO JOINVILLE - GRUPO GISA | K47: 1975878000105 | L47: 9576274000106 | M47: 250.31 | N47: ABASTECIMENTO (DÉBITO) | S47: NFE VINCULADA | T47: I | U47: 2026-08-10 21:00:00.000 -0300 | V47: 250.31 | W47: 4.1260802e+43 | X47: 1. Com nota fiscal recolhida | Y47: 2026-08-15 00:00:00.000 -0300 | Z47: 2026-08-26 00:00:00.000 -0300 | AA47: 443177.07 | AD47: false | AE47: '41260801975878000105550100000025441785364390
A48: 90739624000118 | B48: GRITSCH - PMW | D48: SFL1E46 | E48: COMBUSTÍVEL | F48: 269308 | G48: 2026-08-11 15:23:18.000 -0300 | H48: 25053265 | I48: 99279 | J48: RODOPOSTO | K48: 4219621000111 | L48: 90739624000118 | M48: 298.18 | N48: ABASTECIMENTO (DÉBITO) | S48: NFE VINCULADA | T48: I | U48: 2026-08-11 21:00:00.000 -0300 | V48: 298.18 | W48: 1.7260804e+43 | X48: 1. Com nota fiscal recolhida | Y48: 2026-08-15 00:00:00.000 -0300 | Z48: 2026-08-26 00:00:00.000 -0300 | AA48: 443177.07 | AD48: false | AE48: '17260804219621000111550010000992791349733063
A49: 90739624000118 | B49: GRITSCH - PET | C49: 26248 | D49: TAV9E95 | E49: ARLA | F49: 269308 | G49: 2026-08-11 15:21:18.000 -0300 | H49: 25053242 | J49: SIM REDE - PELOTAS CAVADA 0060-31 - CENTRO RS | K49: 7473735006031 | M49: 42.42 | N49: ABASTECIMENTO (DÉBITO) | S49: PENDENTE DE NOTA | X49: 3. Sem nota fiscal | Y49: 2026-08-15 00:00:00.000 -0300 | Z49: 2026-08-26 00:00:00.000 -0300 | AA49: 443177.07 | AD49: false
A50: 90739624000118 | B50: GRITSCH - RDN | D50: UBA9H34 | E50: COMBUSTÍVEL | F50: 269308 | G50: 2026-08-11 15:19:57.000 -0300 | H50: 25053230 | I50: 53347 | J50: REDE MARAJO BOM JARDIM DE GOIAS | K50: 58446194000133 | L50: 90739624001947 | M50: 501.43 | N50: ABASTECIMENTO (DÉBITO) | S50: NFE VINCULADA | T50: I | U50: 2026-08-10 21:00:00.000 -0300 | V50: 501.43 | W50: 5.2260858e+43 | X50: 1. Com nota fiscal recolhida | Y50: 2026-08-15 00:00:00.000 -0300 | Z50: 2026-08-26 00:00:00.000 -0300 | AA50: 443177.07 | AD50: false | AE50: '52260858446194000133550540000533471818139992
A51: 90739624000118 | B51: GRITSCH - PET | C51: 26248 | D51: TAV9E95 | E51: COMBUSTÍVEL | F51: 269308 | G51: 2026-08-11 15:19:12.000 -0300 | H51: 25053221 | J51: SIM REDE - PELOTAS CAVADA 0060-31 - CENTRO RS | K51: 7473735006031 | M51: 610.96 | N51: ABASTECIMENTO (DÉBITO) | S51: PENDENTE DE NOTA | X51: 3. Sem nota fiscal | Y51: 2026-08-15 00:00:00.000 -0300 | Z51: 2026-08-26 00:00:00.000 -0300 | AA51: 443177.07 | AD51: false
A52: 90739624000118 | B52: GRITSCH - RDN | C52: 23619 | D52: SEL0E76 | E52: ARLA | F52: 269308 | G52: 2026-08-11 15:19:08.000 -0300 | H52: 25053220 | I52: 131912 | J52: POSTO CPN - BR | K52: 23891404000118 | L52: 90739624001866 | M52: 48.25 | N52: ABASTECIMENTO (DÉBITO) | S52: NFE VINCULADA | T52: I | U52: 2026-08-10 21:00:00.000 -0300 | V52: 48.25 | W52: 5.1260824e+43 | X52: 1. Com nota fiscal recolhida | Y52: 2026-08-15 00:00:00.000 -0300 | Z52: 2026-08-26 00:00:00.000 -0300 | AA52: 443177.07 | AD52: false | AE52: '51260823891404000118550110001319121621930536
A53: 90739624000118 | B53: GRITSCH - RDN | C53: 23619 | D53: SEL0E76 | E53: COMBUSTÍVEL | F53: 269308 | G53: 2026-08-11 15:17:45.000 -0300 | H53: 25053155 | I53: 131911 | J53: POSTO CPN - BR | K53: 23891404000118 | L53: 90739624001866 | M53: 403.27 | N53: ABASTECIMENTO (DÉBITO) | S53: NFE VINCULADA | T53: I | U53: 2026-08-10 21:00:00.000 -0300 | V53: 403.27 | W53: 5.1260824e+43 | X53: 1. Com nota fiscal recolhida | Y53: 2026-08-15 00:00:00.000 -0300 | Z53: 2026-08-26 00:00:00.000 -0300 | AA53: 443177.07 | AD53: false | AE53: '51260823891404000118550110001319111895139898
A54: 90739624000118 | B54: GRITSCH - CSC | D54: TAZ4A48 | E54: COMBUSTÍVEL | F54: 269308 | G54: 2026-08-11 15:16:55.000 -0300 | H54: 25053095 | I54: 163210 | J54: POSTO NOVO FOXX - REDE ESTRADA | K54: 2763612000161 | L54: 90739624003133 | M54: 233.9 | N54: ABASTECIMENTO (DÉBITO) | S54: NFE VINCULADA | T54: I | U54: 2026-08-10 21:00:00.000 -0300 | V54: 233.90 | W54: 4.1260803e+43 | X54: 1. Com nota fiscal recolhida | Y54: 2026-08-15 00:00:00.000 -0300 | Z54: 2026-08-26 00:00:00.000 -0300 | AA54: 443177.07 | AD54: false | AE54: '41260802763612000161550020001632101317347268
A55: 90739624000118 | B55: GRITSCH - CWB (BASE) | C55: 25073 | D55: SFM3H40 | E55: COMBUSTÍVEL | F55: 269308 | G55: 2026-08-11 15:06:58.000 -0300 | H55: 25052856 | I55: 389606 | J55: POSTO BARAO MATRIZ|| REDE BARAO | K55: 75176859000155 | L55: 9576274000106 | M55: 244.8 | N55: ABASTECIMENTO (DÉBITO) | S55: NFE VINCULADA | T55: I | U55: 2026-08-10 21:00:00.000 -0300 | V55: 244.80 | W55: 4.1260875e+43 | X55: 1. Com nota fiscal recolhida | Y55: 2026-08-15 00:00:00.000 -0300 | Z55: 2026-08-26 00:00:00.000 -0300 | AA55: 443177.07 | AD55: false | AE55: '41260875176859000155550020003896061768635314
A56: 90739624000118 | B56: GRITSCH - JOI | D56: TAI4J01 | E56: COMBUSTÍVEL | F56: 269308 | G56: 2026-08-11 14:44:25.000 -0300 | H56: 25051437 | I56: 119563 | J56: POSTO ZANDONA 7 | K56: 84711084000161 | L56: 90739624001432 | M56: 273.03 | N56: ABASTECIMENTO (DÉBITO) | S56: NFE VINCULADA | T56: I | U56: 2026-08-10 21:00:00.000 -0300 | V56: 273.03 | W56: 4.2260885e+43 | X56: 1. Com nota fiscal recolhida | Y56: 2026-08-15 00:00:00.000 -0300 | Z56: 2026-08-26 00:00:00.000 -0300 | AA56: 443177.07 | AD56: false | AE56: '42260884711084000161550030001195631111744337
A57: 90739624000118 | B57: GRITSCH - CGB | C57: 21312 | D57: RHS8D32 | E57: COMBUSTÍVEL | F57: 269308 | G57: 2026-08-11 14:40:28.000 -0300 | H57: 25051004 | J57: AMAZONIA - 24 | K57: 9001879002619 | M57: 95.08 | N57: ABASTECIMENTO (DÉBITO) | S57: PENDENTE DE NOTA | X57: 3. Sem nota fiscal | Y57: 2026-08-15 00:00:00.000 -0300 | Z57: 2026-08-26 00:00:00.000 -0300 | AA57: 443177.07 | AD57: false
A58: 90739624000118 | B58: GRITSCH - LDB | D58: TAW7H31 | E58: ARLA | F58: 269308 | G58: 2026-08-11 14:29:03.000 -0300 | H58: 25050039 | I58: 4450 | J58: AUTO POSTO BARUK | K58: 33286065000102 | L58: 9576274000106 | M58: 36.84 | N58: ABASTECIMENTO (DÉBITO) | S58: NFE VINCULADA | T58: I | U58: 2026-08-10 21:00:00.000 -0300 | V58: 36.84 | W58: 4.1260833e+43 | X58: 1. Com nota fiscal recolhida | Y58: 2026-08-15 00:00:00.000 -0300 | Z58: 2026-08-26 00:00:00.000 -0300 | AA58: 443177.07 | AD58: false | AE58: '41260833286065000102550100000044501014216827
A59: 90739624000118 | B59: GRITSCH - PGR | C59: 23456 | D59: SEL2B40 | E59: COMBUSTÍVEL | F59: 269308 | G59: 2026-08-11 14:28:45.000 -0300 | H59: 25050026 | I59: 1150 | J59: POSTO ZAPA MARIUCA | REDE PRIMOS | K59: 27933025000102 | L59: 9576274000106 | M59: 458.95 | N59: ABASTECIMENTO (DÉBITO) | S59: NFE VINCULADA | T59: I | U59: 2026-08-13 21:00:00.000 -0300 | V59: 458.95 | W59: 4.1260828e+43 | X59: 1. Com nota fiscal recolhida | Y59: 2026-08-15 00:00:00.000 -0300 | Z59: 2026-08-26 00:00:00.000 -0300 | AA59: 443177.07 | AD59: false | AE59: '41260827933025000102550090000011501000267280
A60: 90739624000118 | B60: GRITSCH - LDB | D60: TAW7H31 | E60: COMBUSTÍVEL | F60: 269308 | G60: 2026-08-11 14:28:03.000 -0300 | H60: 25049964 | I60: 4449 | J60: AUTO POSTO BARUK | K60: 33286065000102 | L60: 9576274000106 | M60: 758.53 | N60: ABASTECIMENTO (DÉBITO) | S60: NFE VINCULADA | T60: I | U60: 2026-08-10 21:00:00.000 -0300 | V60: 758.53 | W60: 4.1260833e+43 | X60: 1. Com nota fiscal recolhida | Y60: 2026-08-15 00:00:00.000 -0300 | Z60: 2026-08-26 00:00:00.000 -0300 | AA60: 443177.07 | AD60: false | AE60: '41260833286065000102550100000044491014216800
A61: 90739624000118 | B61: GRITSCH - SNO | D61: SFN1H25 | E61: COMBUSTÍVEL | F61: 269308 | G61: 2026-08-11 14:27:09.000 -0300 | H61: 25049882 | I61: 136247 | J61: AUTO POSTO NOVO CEU | K61: 26602128000119 | L61: 90739624001866 | M61: 142.63 | N61: ABASTECIMENTO (DÉBITO) | S61: NFE VINCULADA | T61: I | U61: 2026-08-10 21:00:00.000 -0300 | V61: 142.63 | W61: 5.1260827e+43 | X61: 1. Com nota fiscal recolhida | Y61: 2026-08-15 00:00:00.000 -0300 | Z61: 2026-08-26 00:00:00.000 -0300 | AA61: 443177.07 | AD61: false | AE61: '51260826602128000119550010001362471001773245
A62: 90739624000118 | B62: GRITSCH - CXJ | D62: UBD6I31 | E62: COMBUSTÍVEL | F62: 269308 | G62: 2026-08-11 14:26:45.000 -0300 | H62: 25049849 | J62: SIM REDE - CAXIAS DO SUL 0123-50 - METROPOLITANA / SERRA | K62: 7473735012350 | M62: 377.78 | N62: ABASTECIMENTO (DÉBITO) | S62: PENDENTE DE NOTA | X62: 3. Sem nota fiscal | Y62: 2026-08-15 00:00:00.000 -0300 | Z62: 2026-08-26 00:00:00.000 -0300 | AA62: 443177.07 | AD62: false
A63: 90739624000118 | B63: GRITSCH - CTB | C63: 24143 | D63: SEZ3A79 | E63: COMBUSTÍVEL | F63: 269308 | G63: 2026-08-11 14:22:55.000 -0300 | H63: 25049390 | I63: 168705 | J63: POSTO CAPITAL | K63: 82156977000248 | L63: 90739624001432 | M63: 243.9 | N63: ABASTECIMENTO (DÉBITO) | S63: NFE VINCULADA | T63: I | U63: 2026-08-10 21:00:00.000 -0300 | V63: 243.90 | W63: 4.2260882e+43 | X63: 1. Com nota fiscal recolhida | Y63: 2026-08-15 00:00:00.000 -0300 | Z63: 2026-08-26 00:00:00.000 -0300 | AA63: 443177.07 | AD63: false | AE63: '42260882156977000248550010001687051986882038
A64: 90739624000118 | B64: GRITSCH - MGA | C64: 21147 | D64: RHQ6I66 | E64: COMBUSTÍVEL | F64: 269308 | G64: 2026-08-11 14:22:01.000 -0300 | H64: 25049333 | I64: 16856 | J64: POSTO UNIDO | K64: 79130647000198 | L64: 9576274000106 | M64: 383.75 | N64: ABASTECIMENTO (DÉBITO) | S64: NFE VINCULADA | T64: I | U64: 2026-08-10 21:00:00.000 -0300 | V64: 383.75 | W64: 4.1260879e+43 | X64: 1. Com nota fiscal recolhida | Y64: 2026-08-15 00:00:00.000 -0300 | Z64: 2026-08-26 00:00:00.000 -0300 | AA64: 443177.07 | AD64: false | AE64: '41260879130647000198550050000168561015904426
A65: 90739624000118 | B65: GRITSCH - MGA | C65: 21148 | D65: RHQ6I69 | E65: COMBUSTÍVEL | F65: 269308 | G65: 2026-08-11 14:21:17.000 -0300 | H65: 25049271 | I65: 3023 | J65: POSTO UNIDO | K65: 79130647000198 | L65: 9576274000106 | M65: 61.14 | N65: ABASTECIMENTO (DÉBITO) | S65: NFE VINCULADA | T65: I | U65: 2026-08-10 21:00:00.000 -0300 | V65: 61.14 | W65: 4.1260879e+43 | X65: 1. Com nota fiscal recolhida | Y65: 2026-08-15 00:00:00.000 -0300 | Z65: 2026-08-26 00:00:00.000 -0300 | AA65: 443177.07 | AD65: false | AE65: '41260879130647000198550070000030231015904419
A66: 90739624000118 | B66: GRITSCH - GOI | C66: 23725 | D66: SEN1C56 | E66: COMBUSTÍVEL | F66: 269308 | G66: 2026-08-11 14:20:20.000 -0300 | H66: 25049229 | I66: 81431 | J66: POSTO 10 GOIANIA | REDE CARRETEIRO | K66: 1272434001002 | L66: 90739624001947 | M66: 135.67 | N66: ABASTECIMENTO (DÉBITO) | S66: NFE VINCULADA | T66: I | U66: 2026-08-10 21:00:00.000 -0300 | V66: 135.67 | W66: 5.2260801e+43 | X66: 1. Com nota fiscal recolhida | Y66: 2026-08-15 00:00:00.000 -0300 | Z66: 2026-08-26 00:00:00.000 -0300 | AA66: 443177.07 | AD66: false | AE66: '52260801272434001002550020000814311472286075
A67: 90739624000118 | B67: GRITSCH - MGA | C67: 21141 | D67: RHS3G80 | E67: COMBUSTÍVEL | F67: 269308 | G67: 2026-08-11 14:19:14.000 -0300 | H67: 25049113 | I67: 16855 | J67: POSTO UNIDO | K67: 79130647000198 | L67: 9576274000106 | M67: 440.15 | N67: ABASTECIMENTO (DÉBITO) | S67: NFE VINCULADA | T67: I | U67: 2026-08-10 21:00:00.000 -0300 | V67: 440.15 | W67: 4.1260879e+43 | X67: 1. Com nota fiscal recolhida | Y67: 2026-08-15 00:00:00.000 -0300 | Z67: 2026-08-26 00:00:00.000 -0300 | AA67: 443177.07 | AD67: false | AE67: '41260879130647000198550050000168551015904402
A68: 90739624000118 | B68: GRITSCH - MGA | D68: SFI8F38 | E68: COMBUSTÍVEL | F68: 269308 | G68: 2026-08-11 14:15:16.000 -0300 | H68: 25048768 | I68: 41254 | J68: COCAMAR - MARINGA | REDE COCAMAR MARINGA - PR | K68: 30429333000282 | L68: 9576274000106 | M68: 295.58 | N68: ABASTECIMENTO (DÉBITO) | S68: NFE VINCULADA | T68: I | U68: 2026-08-10 21:00:00.000 -0300 | V68: 295.58 | W68: 4.126083e+43 | X68: 1. Com nota fiscal recolhida | Y68: 2026-08-15 00:00:00.000 -0300 | Z68: 2026-08-26 00:00:00.000 -0300 | AA68: 443177.07 | AD68: false | AE68: '41260830429333000282550110000412541005182783
A69: 90739624000118 | B69: GRITSCH - LDB | D69: UBR9B24 | E69: COMBUSTÍVEL | F69: 269308 | G69: 2026-08-11 14:10:35.000 -0300 | H69: 25048468 | I69: 20903 | J69: AUTO POSTO AMARANTE | K69: 5291412000141 | L69: 9576274000106 | M69: 392.88 | N69: ABASTECIMENTO (DÉBITO) | S69: NFE VINCULADA | T69: I | U69: 2026-08-10 21:00:00.000 -0300 | V69: 392.88 | W69: 4.1260805e+43 | X69: 1. Com nota fiscal recolhida | Y69: 2026-08-15 00:00:00.000 -0300 | Z69: 2026-08-26 00:00:00.000 -0300 | AA69: 443177.07 | AD69: false | AE69: '41260805291412000141550020000209031018184815
A70: 90739624000118 | B70: GRITSCH - RDN | D70: UAV5J69 | E70: COMBUSTÍVEL | F70: 269308 | G70: 2026-08-11 14:09:41.000 -0300 | H70: 25048434 | I70: 3383325 | J70: POSTO TIGRAO - CONFRESA - GRUPO TIGRAO | K70: 3623054000282 | L70: 90739624001866 | M70: 473.75 | N70: ABASTECIMENTO (DÉBITO) | S70: NFE VINCULADA | T70: I | U70: 2026-08-10 21:00:00.000 -0300 | V70: 473.75 | W70: 5.1260804e+43 | X70: 1. Com nota fiscal recolhida | Y70: 2026-08-15 00:00:00.000 -0300 | Z70: 2026-08-26 00:00:00.000 -0300 | AA70: 443177.07 | AD70: false | AE70: '51260803623054000282550010033833251013436995
A71: 90739624000118 | B71: GRITSCH - GOI | D71: TBE5I64 | E71: COMBUSTÍVEL | F71: 269308 | G71: 2026-08-11 14:03:09.000 -0300 | H71: 25047882 | I71: 81429 | J71: POSTO 10 GOIANIA | REDE CARRETEIRO | K71: 1272434001002 | L71: 90739624001947 | M71: 291.87 | N71: ABASTECIMENTO (DÉBITO) | S71: NFE VINCULADA | T71: I | U71: 2026-08-10 21:00:00.000 -0300 | V71: 291.87 | W71: 5.2260801e+43 | X71: 1. Com nota fiscal recolhida | Y71: 2026-08-15 00:00:00.000 -0300 | Z71: 2026-08-26 00:00:00.000 -0300 | AA71: 443177.07 | AD71: false | AE71: '52260801272434001002550020000814291705266782
A72: 90739624000118 | B72: GRITSCH - PGR | D72: SDR8E10 | E72: COMBUSTÍVEL | F72: 269308 | G72: 2026-08-11 14:02:55.000 -0300 | H72: 25047875 | I72: 1149 | J72: POSTO ZAPA MARIUCA | REDE PRIMOS | K72: 27933025000102 | L72: 9576274000106 | M72: 214.09 | N72: ABASTECIMENTO (DÉBITO) | S72: NFE VINCULADA | T72: I | U72: 2026-08-13 21:00:00.000 -0300 | V72: 214.09 | W72: 4.1260828e+43 | X72: 1. Com nota fiscal recolhida | Y72: 2026-08-15 00:00:00.000 -0300 | Z72: 2026-08-26 00:00:00.000 -0300 | AA72: 443177.07 | AD72: false | AE72: '41260827933025000102550090000011491000267271
A73: 90739624000118 | B73: GRITSCH - CHA | D73: UBR9B25 | E73: COMBUSTÍVEL | F73: 269308 | G73: 2026-08-11 13:59:42.000 -0300 | H73: 25047830 | I73: 59392 | J73: POSTO NATAL - MAXSUL | K73: 20630766000167 | L73: 90739624001432 | M73: 269.16 | N73: ABASTECIMENTO (DÉBITO) | S73: NFE VINCULADA | T73: I | U73: 2026-08-10 21:00:00.000 -0300 | V73: 269.16 | W73: 4.2260821e+43 | X73: 1. Com nota fiscal recolhida | Y73: 2026-08-15 00:00:00.000 -0300 | Z73: 2026-08-26 00:00:00.000 -0300 | AA73: 443177.07 | AD73: false | AE73: '42260820630766000167550040000593921808428894
A74: 90739624000118 | B74: GRITSCH - GOI | D74: TBE5I66 | E74: COMBUSTÍVEL | F74: 269308 | G74: 2026-08-11 13:53:38.000 -0300 | H74: 25047120 | I74: 27326 | J74: POSTO SAO JUDAS TADEU - REDE Z+Z (RODOVIA) | K74: 13759928000104 | L74: 90739624001947 | M74: 230.17 | N74: ABASTECIMENTO (DÉBITO) | S74: NFE VINCULADA | T74: I | U74: 2026-08-10 21:00:00.000 -0300 | V74: 230.17 | W74: 5.2260814e+43 | X74: 1. Com nota fiscal recolhida | Y74: 2026-08-15 00:00:00.000 -0300 | Z74: 2026-08-26 00:00:00.000 -0300 | AA74: 443177.07 | AD74: false | AE74: '52260813759928000104550040000273261005194696
A75: 90739624000118 | B75: GRITSCH - PBC | C75: 23458 | D75: SEL1F32 | E75: COMBUSTÍVEL | F75: 269308 | G75: 2026-08-11 13:53:30.000 -0300 | H75: 25047087 | I75: 257432 | J75: GP POSTOS - POSTO TREVO | K75: 79964177000168 | L75: 9576274000106 | M75: 176.12 | N75: ABASTECIMENTO (DÉBITO) | S75: NFE VINCULADA | T75: I | U75: 2026-08-10 21:00:00.000 -0300 | V75: 176.12 | W75: 4.126088e+43 | X75: 1. Com nota fiscal recolhida | Y75: 2026-08-15 00:00:00.000 -0300 | Z75: 2026-08-26 00:00:00.000 -0300 | AA75: 443177.07 | AD75: false | AE75: '41260879964177000168550020002574321015043171
A76: 90739624000118 | B76: GRITSCH - GOI | D76: UBW4G97 | E76: COMBUSTÍVEL | F76: 269308 | G76: 2026-08-11 13:52:56.000 -0300 | H76: 25047034 | I76: 81427 | J76: POSTO 10 GOIANIA | REDE CARRETEIRO | K76: 1272434001002 | L76: 90739624001947 | M76: 144.99 | N76: ABASTECIMENTO (DÉBITO) | S76: NFE VINCULADA | T76: I | U76: 2026-08-10 21:00:00.000 -0300 | V76: 144.99 | W76: 5.2260801e+43 | X76: 1. Com nota fiscal recolhida | Y76: 2026-08-15 00:00:00.000 -0300 | Z76: 2026-08-26 00:00:00.000 -0300 | AA76: 443177.07 | AD76: false | AE76: '52260801272434001002550020000814271895102030
A77: 90739624000118 | B77: GRITSCH - PGR | D77: SED9B31 | E77: COMBUSTÍVEL | F77: 269308 | G77: 2026-08-11 13:44:14.000 -0300 | H77: 25046610 | I77: 1148 | J77: POSTO ZAPA MARIUCA | REDE PRIMOS | K77: 27933025000102 | L77: 9576274000106 | M77: 265.72 | N77: ABASTECIMENTO (DÉBITO) | S77: NFE VINCULADA | T77: I | U77: 2026-08-13 21:00:00.000 -0300 | V77: 265.72 | W77: 4.1260828e+43 | X77: 1. Com nota fiscal recolhida | Y77: 2026-08-15 00:00:00.000 -0300 | Z77: 2026-08-26 00:00:00.000 -0300 | AA77: 443177.07 | AD77: false | AE77: '41260827933025000102550090000011481000267266
A78: 90739624000118 | B78: GRITSCH - MGA | D78: SEE9E85 | E78: COMBUSTÍVEL | F78: 269308 | G78: 2026-08-11 13:43:04.000 -0300 | H78: 25046499 | I78: 41248 | J78: COCAMAR - MARINGA | REDE COCAMAR MARINGA - PR | K78: 30429333000282 | L78: 9576274000106 | M78: 167.13 | N78: ABASTECIMENTO (DÉBITO) | S78: NFE VINCULADA | T78: I | U78: 2026-08-10 21:00:00.000 -0300 | V78: 167.13 | W78: 4.126083e+43 | X78: 1. Com nota fiscal recolhida | Y78: 2026-08-15 00:00:00.000 -0300 | Z78: 2026-08-26 00:00:00.000 -0300 | AA78: 443177.07 | AD78: false | AE78: '41260830429333000282550110000412481005182417
A79: 90739624000118 | B79: GRITSCH - GOI | C79: 20087 | D79: RHC1F97 | E79: COMBUSTÍVEL | F79: 269308 | G79: 2026-08-11 13:41:25.000 -0300 | H79: 25046365 | I79: 38312 | J79: AUTO POSTO CIDADE - PORANGATU | K79: 33360405000190 | L79: 90739624001947 | M79: 345.14 | N79: ABASTECIMENTO (DÉBITO) | S79: NFE VINCULADA | T79: I | U79: 2026-08-10 21:00:00.000 -0300 | V79: 345.14 | W79: 5.2260833e+43 | X79: 1. Com nota fiscal recolhida | Y79: 2026-08-15 00:00:00.000 -0300 | Z79: 2026-08-26 00:00:00.000 -0300 | AA79: 443177.07 | AD79: false | AE79: '52260833360405000190550020000383121008886813
A80: 90739624000118 | B80: GRITSCH - GOI | C80: 24445 | D80: SFD2H32 | E80: COMBUSTÍVEL | F80: 269308 | G80: 2026-08-11 13:40:18.000 -0300 | H80: 25046327 | I80: 38313 | J80: AUTO POSTO CIDADE - PORANGATU | K80: 33360405000190 | L80: 90739624001947 | M80: 343.4 | N80: ABASTECIMENTO (DÉBITO) | S80: NFE VINCULADA | T80: I | U80: 2026-08-10 21:00:00.000 -0300 | V80: 343.40 | W80: 5.2260833e+43 | X80: 1. Com nota fiscal recolhida | Y80: 2026-08-15 00:00:00.000 -0300 | Z80: 2026-08-26 00:00:00.000 -0300 | AA80: 443177.07 | AD80: false | AE80: '52260833360405000190550020000383131008886829
A81: 90739624000118 | B81: GRITSCH - CSC | C81: 22473 | D81: SDU9F93 | E81: COMBUSTÍVEL | F81: 269308 | G81: 2026-08-11 13:39:23.000 -0300 | H81: 25046278 | I81: 163199 | J81: POSTO NOVO FOXX - REDE ESTRADA | K81: 2763612000161 | L81: 90739624003133 | M81: 231.6 | N81: ABASTECIMENTO (DÉBITO) | S81: NFE VINCULADA | T81: I | U81: 2026-08-10 21:00:00.000 -0300 | V81: 231.60 | W81: 4.1260803e+43 | X81: 1. Com nota fiscal recolhida | Y81: 2026-08-15 00:00:00.000 -0300 | Z81: 2026-08-26 00:00:00.000 -0300 | AA81: 443177.07 | AD81: false | AE81: '41260802763612000161550020001631991078858250
A82: 90739624000118 | B82: GRITSCH - PBC | C82: 24139 | D82: SEY5E62 | E82: COMBUSTÍVEL | F82: 269308 | G82: 2026-08-11 13:33:31.000 -0300 | H82: 25045978 | I82: 257429 | J82: GP POSTOS - POSTO TREVO | K82: 79964177000168 | L82: 9576274000106 | M82: 450.99 | N82: ABASTECIMENTO (DÉBITO) | S82: NFE VINCULADA | T82: I | U82: 2026-08-10 21:00:00.000 -0300 | V82: 450.99 | W82: 4.126088e+43 | X82: 1. Com nota fiscal recolhida | Y82: 2026-08-15 00:00:00.000 -0300 | Z82: 2026-08-26 00:00:00.000 -0300 | AA82: 443177.07 | AD82: false | AE82: '41260879964177000168550020002574291015043095
A83: 90739624000118 | B83: GRITSCH - SNO | D83: TAJ6B89 | E83: COMBUSTÍVEL | F83: 269308 | G83: 2026-08-11 13:30:58.000 -0300 | H83: 25045941 | I83: 10549 | J83: AUTO POSTO PASQUALOTTO | JURUENA | K83: 8512459000690 | L83: 90739624001866 | M83: 186.39 | N83: ABASTECIMENTO (DÉBITO) | S83: NFE VINCULADA | T83: I | U83: 2026-08-10 21:00:00.000 -0300 | V83: 186.40 | W83: 5.1260809e+43 | X83: 1. Com nota fiscal recolhida | Y83: 2026-08-15 00:00:00.000 -0300 | Z83: 2026-08-26 00:00:00.000 -0300 | AA83: 443177.07 | AD83: false | AE83: '51260808512459000690550130000105491864811456
A84: 90739624000118 | B84: GRITSCH - SNO | D84: TAI4I80 | E84: COMBUSTÍVEL | F84: 269308 | G84: 2026-08-11 13:28:11.000 -0300 | H84: 25045849 | I84: 1817 | J84: REDE DINO - BANDEIRANTES AUTO POSTO | K84: 8603562001103 | L84: 90739624001866 | M84: 115.35 | N84: ABASTECIMENTO (DÉBITO) | S84: NFE VINCULADA | T84: I | U84: 2026-08-10 21:00:00.000 -0300 | V84: 115.35 | W84: 5.1260809e+43 | X84: 1. Com nota fiscal recolhida | Y84: 2026-08-15 00:00:00.000 -0300 | Z84: 2026-08-26 00:00:00.000 -0300 | AA84: 443177.07 | AD84: false | AE84: '51260808603562001103550080000018171304223646
A85: 90739624000118 | B85: GRITSCH - MGA | C85: 23848 | D85: SEP6E28 | E85: COMBUSTÍVEL | F85: 269308 | G85: 2026-08-11 13:21:40.000 -0300 | H85: 25045716 | I85: 41244 | J85: COCAMAR - MARINGA | REDE COCAMAR MARINGA - PR | K85: 30429333000282 | L85: 9576274000106 | M85: 127.72 | N85: ABASTECIMENTO (DÉBITO) | S85: NFE VINCULADA | T85: I | U85: 2026-08-10 21:00:00.000 -0300 | V85: 127.72 | W85: 4.126083e+43 | X85: 1. Com nota fiscal recolhida | Y85: 2026-08-15 00:00:00.000 -0300 | Z85: 2026-08-26 00:00:00.000 -0300 | AA85: 443177.07 | AD85: false | AE85: '41260830429333000282550110000412441005181977
A86: 90739624000118 | B86: GRITSCH - CHA | D86: SFN1H57 | E86: COMBUSTÍVEL | F86: 269308 | G86: 2026-08-11 13:15:39.000 -0300 | H86: 25045572 | I86: 716 | J86: POSTO NP LESTE| REDE MAXSUL | K86: 65580965000146 | L86: 90739624001432 | M86: 230.36 | N86: ABASTECIMENTO (DÉBITO) | S86: NFE VINCULADA | T86: I | U86: 2026-08-10 21:00:00.000 -0300 | V86: 230.36 | W86: 4.2260866e+43 | X86: 1. Com nota fiscal recolhida | Y86: 2026-08-15 00:00:00.000 -0300 | Z86: 2026-08-26 00:00:00.000 -0300 | AA86: 443177.07 | AD86: false | AE86: '42260865580965000146550060000007161477560520
A87: 90739624000118 | B87: GRITSCH - CGR | D87: SFG4I63 | E87: COMBUSTÍVEL | F87: 269308 | G87: 2026-08-11 13:17:46.000 -0300 | H87: 25045567 | I87: 16233 | J87: POSTO FIGUEIRA - CAMPO GRANDE | K87: 2322969000104 | L87: 90739624001190 | M87: 252.02 | N87: ABASTECIMENTO (DÉBITO) | S87: NFE VINCULADA | T87: I | U87: 2026-08-10 21:00:00.000 -0300 | V87: 252.02 | W87: 5.0260802e+43 | X87: 1. Com nota fiscal recolhida | Y87: 2026-08-15 00:00:00.000 -0300 | Z87: 2026-08-26 00:00:00.000 -0300 | AA87: 443177.07 | AD87: false | AE87: '50260802322969000104550020000162331003503369
A88: 90739624000118 | B88: GRITSCH - PMW | D88: UAV5J75 | E88: COMBUSTÍVEL | F88: 269308 | G88: 2026-08-11 13:14:43.000 -0300 | H88: 25045522 | I88: 99278 | J88: RODOPOSTO | K88: 4219621000111 | L88: 90739624000118 | M88: 249.84 | N88: ABASTECIMENTO (DÉBITO) | S88: NFE VINCULADA | T88: I | U88: 2026-08-11 21:00:00.000 -0300 | V88: 249.84 | W88: 1.7260804e+43 | X88: 1. Com nota fiscal recolhida | Y88: 2026-08-15 00:00:00.000 -0300 | Z88: 2026-08-26 00:00:00.000 -0300 | AA88: 443177.07 | AD88: false | AE88: '17260804219621000111550010000992781179451391
A89: 90739624000118 | B89: GRITSCH - CHA | C89: 26140 | D89: TAS4G97 | E89: COMBUSTÍVEL | F89: 269308 | G89: 2026-08-11 13:12:27.000 -0300 | H89: 25045489 | I89: 59198 | J89: POSTO NATAL - MAXSUL | K89: 20630766000167 | L89: 90739624001432 | M89: 209.75 | N89: ABASTECIMENTO (DÉBITO) | S89: NFE VINCULADA | T89: I | U89: 2026-08-10 21:00:00.000 -0300 | V89: 209.75 | W89: 4.2260821e+43 | X89: 1. Com nota fiscal recolhida | Y89: 2026-08-15 00:00:00.000 -0300 | Z89: 2026-08-26 00:00:00.000 -0300 | AA89: 443177.07 | AD89: false | AE89: '42260820630766000167550050000591981310358288
A90: 90739624000118 | B90: GRITSCH - PGR | C90: 23840 | D90: SEP6E17 | E90: COMBUSTÍVEL | F90: 269308 | G90: 2026-08-11 13:09:44.000 -0300 | H90: 25045445 | I90: 1146 | J90: POSTO ZAPA MARIUCA | REDE PRIMOS | K90: 27933025000102 | L90: 9576274000106 | M90: 41.03 | N90: ABASTECIMENTO (DÉBITO) | S90: NFE VINCULADA | T90: I | U90: 2026-08-13 21:00:00.000 -0300 | V90: 41.03 | W90: 4.1260828e+43 | X90: 1. Com nota fiscal recolhida | Y90: 2026-08-15 00:00:00.000 -0300 | Z90: 2026-08-26 00:00:00.000 -0300 | AA90: 443177.07 | AD90: false | AE90: '41260827933025000102550090000011461000267237
A91: 90739624000118 | B91: GRITSCH - CXJ | D91: SDU9F54 | E91: COMBUSTÍVEL | F91: 269308 | G91: 2026-08-11 13:08:46.000 -0300 | H91: 25045427 | J91: SIM REDE - CAXIAS FESTA DA UVA 0015-87 - METROPOLITANA / SERRA | K91: 7473735001587 | M91: 126.76 | N91: ABASTECIMENTO (DÉBITO) | S91: PENDENTE DE NOTA | X91: 3. Sem nota fiscal | Y91: 2026-08-15 00:00:00.000 -0300 | Z91: 2026-08-26 00:00:00.000 -0300 | AA91: 443177.07 | AD91: false
A92: 90739624000118 | B92: GRITSCH - PBC | D92: UBK4B57 | E92: COMBUSTÍVEL | F92: 269308 | G92: 2026-08-11 13:02:08.000 -0300 | H92: 25045243 | I92: 257424 | J92: GP POSTOS - POSTO TREVO | K92: 79964177000168 | L92: 9576274000106 | M92: 283.05 | N92: ABASTECIMENTO (DÉBITO) | S92: NFE VINCULADA | T92: I | U92: 2026-08-10 21:00:00.000 -0300 | V92: 283.05 | W92: 4.126088e+43 | X92: 1. Com nota fiscal recolhida | Y92: 2026-08-15 00:00:00.000 -0300 | Z92: 2026-08-26 00:00:00.000 -0300 | AA92: 443177.07 | AD92: false | AE92: '41260879964177000168550020002574241015042866
A93: 90739624000118 | B93: GRITSCH - BLN | C93: 24444 | D93: SFD2H30 | E93: COMBUSTÍVEL | F93: 269308 | G93: 2026-08-11 12:57:24.000 -0300 | H93: 25045086 | I93: 130093 | J93: POSTO ZANDONA 12 | K93: 83392050000199 | L93: 90739624001432 | M93: 137.08 | N93: ABASTECIMENTO (DÉBITO) | S93: NFE VINCULADA | T93: I | U93: 2026-08-10 21:00:00.000 -0300 | V93: 137.08 | W93: 4.2260883e+43 | X93: 1. Com nota fiscal recolhida | Y93: 2026-08-15 00:00:00.000 -0300 | Z93: 2026-08-26 00:00:00.000 -0300 | AA93: 443177.07 | AD93: false | AE93: '42260883392050000199550020001300931111557301
A94: 90739624000118 | B94: GRITSCH - LDB | C94: 21139 | D94: RHS3G79 | E94: COMBUSTÍVEL | F94: 269308 | G94: 2026-08-11 12:50:51.000 -0300 | H94: 25045007 | I94: 9441 | J94: AUTO POSTO CHEGADAO | K94: 3680814000102 | L94: 9576274000106 | M94: 416.12 | N94: ABASTECIMENTO (DÉBITO) | S94: NFE VINCULADA | T94: I | U94: 2026-08-10 21:00:00.000 -0300 | V94: 416.12 | W94: 4.1260804e+43 | X94: 1. Com nota fiscal recolhida | Y94: 2026-08-15 00:00:00.000 -0300 | Z94: 2026-08-26 00:00:00.000 -0300 | AA94: 443177.07 | AD94: false | AE94: '41260803680814000102550080000094411245056450
A95: 90739624000118 | B95: GRITSCH - PGR | C95: 22486 | D95: SDU9F80 | E95: COMBUSTÍVEL | F95: 269308 | G95: 2026-08-11 12:43:45.000 -0300 | H95: 25044827 | J95: POSTO ZAPA MARIUCA | REDE PRIMOS | K95: 27933025000102 | M95: 99.07 | N95: ABASTECIMENTO (DÉBITO) | S95: PENDENTE DE NOTA | X95: 3. Sem nota fiscal | Y95: 2026-08-15 00:00:00.000 -0300 | Z95: 2026-08-26 00:00:00.000 -0300 | AA95: 443177.07 | AD95: false
A96: 90739624000118 | B96: GRITSCH - POA | D96: SEP6E19 | E96: COMBUSTÍVEL | F96: 269308 | G96: 2026-08-11 12:38:55.000 -0300 | H96: 25044744 | I96: 1667 | J96: BUFFON 30 - BANDEIRA BRANCA | K96: 93489243003050 | L96: 90739624002323 | M96: 272.66 | N96: ABASTECIMENTO (DÉBITO) | S96: NFE VINCULADA | T96: I | U96: 2026-08-10 21:00:00.000 -0300 | V96: 272.66 | W96: 4.3260893e+43 | X96: 1. Com nota fiscal recolhida | Y96: 2026-08-15 00:00:00.000 -0300 | Z96: 2026-08-26 00:00:00.000 -0300 | AA96: 443177.07 | AD96: false | AE96: '43260893489243003050550040000016671561601521
A97: 90739624000118 | B97: GRITSCH - MGA | C97: 22492 | D97: SDU9F62 | E97: COMBUSTÍVEL | F97: 269308 | G97: 2026-08-11 12:38:20.000 -0300 | H97: 25044738 | I97: 41235 | J97: COCAMAR - MARINGA | REDE COCAMAR MARINGA - PR | K97: 30429333000282 | L97: 9576274000106 | M97: 176.21 | N97: ABASTECIMENTO (DÉBITO) | S97: NFE VINCULADA | T97: I | U97: 2026-08-10 21:00:00.000 -0300 | V97: 176.21 | W97: 4.126083e+43 | X97: 1. Com nota fiscal recolhida | Y97: 2026-08-15 00:00:00.000 -0300 | Z97: 2026-08-26 00:00:00.000 -0300 | AA97: 443177.07 | AD97: false | AE97: '41260830429333000282550110000412351005181285
A98: 90739624000118 | B98: GRITSCH - CGB | C98: 22137 | D98: SDT4B70 | E98: COMBUSTÍVEL | F98: 269308 | G98: 2026-08-11 12:37:22.000 -0300 | H98: 25044722 | I98: 54921 | J98: REDE DINO - POSTO TREVINHO | K98: 8603562000212 | L98: 90739624001866 | M98: 83.8 | N98: ABASTECIMENTO (DÉBITO) | S98: NFE VINCULADA | T98: I | U98: 2026-08-10 21:00:00.000 -0300 | V98: 83.80 | W98: 5.1260809e+43 | X98: 1. Com nota fiscal recolhida | Y98: 2026-08-15 00:00:00.000 -0300 | Z98: 2026-08-26 00:00:00.000 -0300 | AA98: 443177.07 | AD98: false | AE98: '51260808603562000212550050000549211011645383
A99: 90739624000118 | B99: GRITSCH - CXJ | D99: UBM2C03 | E99: COMBUSTÍVEL | F99: 269308 | G99: 2026-08-11 12:32:52.000 -0300 | H99: 25044652 | J99: SIM REDE - CAXIAS FESTA DA UVA 0015-87 - METROPOLITANA / SERRA | K99: 7473735001587 | M99: 271.04 | N99: ABASTECIMENTO (DÉBITO) | S99: PENDENTE DE NOTA | X99: 3. Sem nota fiscal | Y99: 2026-08-15 00:00:00.000 -0300 | Z99: 2026-08-26 00:00:00.000 -0300 | AA99: 443177.07 | AD99: false
A100: 90739624000118 | B100: GRITSCH - POA | C100: 26122 | D100: TAS4H12 | E100: COMBUSTÍVEL | F100: 269308 | G100: 2026-08-11 12:32:11.000 -0300 | H100: 25044538 | J100: SIM REDE - TORRES 0062-01 - SC SUL | K100: 7473735006201 | M100: 227.45 | N100: ABASTECIMENTO (DÉBITO) | S100: PENDENTE DE NOTA | X100: 3. Sem nota fiscal | Y100: 2026-08-15 00:00:00.000 -0300 | Z100: 2026-08-26 00:00:00.000 -0300 | AA100: 443177.07 | AD100: false
...

Sheet Relatorio
A1: fatura | B1: categoria_relatorio | C1: placa | D1: garagem | E1: data_transacao | F1: id_transacao_atual | G1: nome_posto | H1: cnpj_posto | I1: cnpj_filial_nfe | J1: natureza_bluefllet | K1: valor_item_liquido | L1: status_fiscal | M1: numero_nota_fiscal | N1: nfe_data_emissao | O1: nfe_valor_nota | P1: chave_nfe | Q1: id_referencia_original | R1: fatura_origem_referencia | S1: fatura_credito_retorno | T1: data_credito_retorno | U1: titulo_data_vencimento
A2: 269308 | B2: 4. Crédito de estorno (desconto) | C2: SFL2F19 | D2: GRITSCH - CGB | E2: 2026-08-01 14:03:55.000 -0300 | F2: 25041264 | G2: POSTO SAO JOSE 1 | H2: 4903852000140 | J2: COMBUSTÍVEL | K2: -285.67 | L2: CRÉDITO / ESTORNO | Q2: 24567446 | R2: 267384 | U2: 2026-08-26 00:00:00.000 -0300
A3: 269308 | B3: 4. Crédito de estorno (desconto) | C3: UBR9A92 | D3: GRITSCH - POA | E3: 2026-07-28 18:26:06.000 -0300 | F3: 25041210 | G3: SIM REDE - ALEGRETE - 019877 - CENTRO RS | H3: 7473735019877 | J3: COMBUSTÍVEL | K3: -251.86 | L3: CRÉDITO / ESTORNO | Q3: 24375893 | R3: 267384 | U3: 2026-08-26 00:00:00.000 -0300
A4: 269308 | B4: 4. Crédito de estorno (desconto) | C4: UBN9E24 | D4: GRITSCH - PET | E4: 2026-07-31 08:16:17.000 -0300 | F4: 25030298 | G4: SIM REDE - PELOTAS FERNANDO OSORIO 0093-08 - CENTRO RS | H4: 7473735009308 | J4: COMBUSTÍVEL | K4: -141.68 | L4: CRÉDITO / ESTORNO | Q4: 24502758 | R4: 267384 | U4: 2026-08-26 00:00:00.000 -0300
A5: 269308 | B5: 4. Crédito de estorno (desconto) | C5: SDU9F98 | D5: GRITSCH - RVD | E5: 2026-08-07 10:14:51.000 -0300 | F5: 24861044 | G5: POSTO ALDO JATAI INDUSTRIAL - REDE ALDO | H5: 2651099000117 | J5: COMBUSTÍVEL | K5: -331.89 | L5: CRÉDITO / ESTORNO | Q5: 24860705 | R5: 269308 | U5: 2026-08-26 00:00:00.000 -0300
A6: 269308 | B6: 4. Crédito de estorno (desconto) | C6: TBE5I66 | D6: GRITSCH - GOI | E6: 2026-08-03 14:18:13.000 -0300 | F6: 25027473 | G6: POSTO SAO JUDAS TADEU - REDE Z+Z (RODOVIA) | H6: 13759928000104 | J6: COMBUSTÍVEL | K6: -231.70 | L6: CRÉDITO / ESTORNO | Q6: 24661956 | R6: 267384 | U6: 2026-08-26 00:00:00.000 -0300
A7: 269308 | B7: 4. Crédito de estorno (desconto) | C7: TBE5I66 | D7: GRITSCH - GOI | E7: 2026-07-30 15:13:04.000 -0300 | F7: 25029954 | G7: POSTO SAO JUDAS TADEU - REDE Z+Z (RODOVIA) | H7: 13759928000104 | J7: COMBUSTÍVEL | K7: -225.77 | L7: CRÉDITO / ESTORNO | Q7: 24469630 | R7: 267384 | U7: 2026-08-26 00:00:00.000 -0300
A8: 269308 | B8: 1. Com nota fiscal recolhida | C8: SFH7D75 | D8: GRITSCH - MATRIZ | E8: 2026-08-11 20:32:34.000 -0300 | F8: 25063040 | G8: POSTO 2 IRMAOS | H8: 76493295000147 | I8: 9576274000106 | J8: COMBUSTÍVEL | K8: 252.02 | L8: NFE VINCULADA | M8: 29106 | N8: 2026-08-10 21:00:00.000 -0300 | O8: 252.02 | P8: '41260876493295000147550020000291061002782187 | U8: 2026-08-26 00:00:00.000 -0300
A9: 269308 | B9: 1. Com nota fiscal recolhida | C9: TBK1J24 | D9: GRITSCH - RVD | E9: 2026-08-11 20:16:50.000 -0300 | F9: 25062781 | G9: REDE MONTE CARLO - POSTO SAO JOSE | H9: 42733072000198 | I9: 90739624000380 | J9: COMBUSTÍVEL | K9: 283.60 | L9: NFE VINCULADA | M9: 5325 | N9: 2026-08-11 21:00:00.000 -0300 | O9: 283.60 | P9: '35260842733072000198550080000053251524484620 | U9: 2026-08-26 00:00:00.000 -0300
A10: 269308 | B10: 1. Com nota fiscal recolhida | C10: UAV5J73 | D10: GRITSCH - GOI | E10: 2026-08-11 19:42:40.000 -0300 | F10: 25062357 | G10: AUTO POSTO CIDADE - PORANGATU | H10: 33360405000190 | I10: 90739624001947 | J10: COMBUSTÍVEL | K10: 220.77 | L10: NFE VINCULADA | M10: 38315 | N10: 2026-08-10 21:00:00.000 -0300 | O10: 220.77 | P10: '52260833360405000190550020000383151008888133 | U10: 2026-08-26 00:00:00.000 -0300
A11: 269308 | B11: 1. Com nota fiscal recolhida | C11: UCB6D90 | D11: GRITSCH - SAO (PERUS) | E11: 2026-08-11 19:17:08.000 -0300 | F11: 25061999 | G11: POSTO DO TREVO - REDE GRAAL | H11: 55973291000196 | I11: 90739624000380 | J11: COMBUSTÍVEL | K11: 336.50 | L11: NFE VINCULADA | M11: 1052949 | N11: 2026-08-10 21:00:00.000 -0300 | O11: 336.50 | P11: '35260855973291000196550030010529491018448930 | U11: 2026-08-26 00:00:00.000 -0300
A12: 269308 | B12: 1. Com nota fiscal recolhida | C12: UCC8A40 | D12: GRITSCH - CWB (BASE) | E12: 2026-08-11 19:14:36.000 -0300 | F12: 25061890 | G12: GP POSTOS - POSTO SAO JOSE | H12: 79964177000591 | I12: 9576274000106 | J12: COMBUSTÍVEL | K12: 698.82 | L12: NFE VINCULADA | M12: 820855 | N12: 2026-08-10 21:00:00.000 -0300 | O12: 698.82 | P12: '41260879964177000591550020008208551011758525 | U12: 2026-08-26 00:00:00.000 -0300
A13: 269308 | B13: 1. Com nota fiscal recolhida | C13: UAV5J75 | D13: GRITSCH - PMW | E13: 2026-08-11 19:09:13.000 -0300 | F13: 25061863 | G13: AUTO POSTO CIDADE - PORANGATU | H13: 33360405000190 | I13: 90739624001947 | J13: COMBUSTÍVEL | K13: 196.89 | L13: NFE VINCULADA | M13: 38314 | N13: 2026-08-10 21:00:00.000 -0300 | O13: 196.89 | P13: '52260833360405000190550020000383141008887997 | U13: 2026-08-26 00:00:00.000 -0300
A14: 269308 | B14: 1. Com nota fiscal recolhida | C14: BBW0C96 | D14: GRITSCH - CWB (BASE) | E14: 2026-08-11 18:36:53.000 -0300 | F14: 25061415 | G14: GP POSTOS - POSTO SAO JOSE | H14: 79964177000591 | I14: 9576274000106 | J14: COMBUSTÍVEL | K14: 1878.84 | L14: NFE VINCULADA | M14: 820852 | N14: 2026-08-10 21:00:00.000 -0300 | O14: 1878.84 | P14: '41260879964177000591550020008208521011758434 | U14: 2026-08-26 00:00:00.000 -0300
A15: 269308 | B15: 1. Com nota fiscal recolhida | C15: RHT0B69 | D15: GRITSCH - CHA | E15: 2026-08-11 18:33:59.000 -0300 | F15: 25061399 | G15: BUFFON 74 | H15: 93489243007471 | I15: 90739624002323 | J15: COMBUSTÍVEL | K15: 475.60 | L15: NFE VINCULADA | M15: 4439 | N15: 2026-08-10 21:00:00.000 -0300 | O15: 475.60 | P15: '43260893489243007471550080000044391522201280 | U15: 2026-08-26 00:00:00.000 -0300
A16: 269308 | B16: 1. Com nota fiscal recolhida | C16: TBE5I62 | D16: GRITSCH - GOI | E16: 2026-08-11 17:34:10.000 -0300 | F16: 25056047 | G16: POSTO 10 GOIANIA | REDE CARRETEIRO | H16: 1272434001002 | I16: 90739624001947 | J16: COMBUSTÍVEL | K16: 260.28 | L16: NFE VINCULADA | M16: 81440 | N16: 2026-08-10 21:00:00.000 -0300 | O16: 260.28 | P16: '52260801272434001002550020000814401274796734 | U16: 2026-08-26 00:00:00.000 -0300
A17: 269308 | B17: 1. Com nota fiscal recolhida | C17: TAS4H20 | D17: GRITSCH - SAO (PERUS) | E17: 2026-08-11 17:25:18.000 -0300 | F17: 25055879 | G17: AUTO POSTO LIMOEIRO - PALOMA - REDE GRAAL | H17: 5065447000162 | I17: 90739624000380 | J17: COMBUSTÍVEL | K17: 221.63 | L17: NFE VINCULADA | M17: 374251 | N17: 2026-08-10 21:00:00.000 -0300 | O17: 221.63 | P17: '35260805065447000162550060003742511006200254 | U17: 2026-08-26 00:00:00.000 -0300
A18: 269308 | B18: 1. Com nota fiscal recolhida | C18: SEI5B85 | D18: GRITSCH - RDN | E18: 2026-08-11 17:22:05.000 -0300 | F18: 25055759 | G18: REDE DINO - POSTO SERRA DAS ARARAS | H18: 50128357000551 | I18: 90739624001866 | J18: COMBUSTÍVEL | K18: 189.65 | L18: NFE VINCULADA | M18: 10286 | N18: 2026-08-10 21:00:00.000 -0300 | O18: 189.64 | P18: '51260850128357000551550050000102861001035117 | U18: 2026-08-26 00:00:00.000 -0300
A19: 269308 | B19: 1. Com nota fiscal recolhida | C19: TAI9A24 | D19: GRITSCH - POA | E19: 2026-08-11 17:17:58.000 -0300 | F19: 25055716 | G19: SIM REDE - ALEGRETE - 019877 - CENTRO RS | H19: 7473735019877 | I19: 90739624002323 | J19: COMBUSTÍVEL | K19: 255.16 | L19: NFE VINCULADA | M19: 58070 | N19: 2026-08-10 21:00:00.000 -0300 | O19: 255.16 | P19: '43260807473735019877550080000580701009183062 | U19: 2026-08-26 00:00:00.000 -0300
... A45: 269308 | B45: 1. Com nota fiscal recolhida | C45: TAI9A19 | D45: GRITSCH - GOI | E45: 2026-08-11 15:34:32.000 -0300 | F45: 25053634 | G45: POSTO CALIFORNIA - PASADENA | H45: 47377960000139 | I45: 90739624001947 | J45: COMBUSTÍVEL | K45: 210.91 | L45: NFE VINCULADA | M45: 113417 | N45: 2026-08-10 21:00:00.000 -0300 | O45: 210.90 | P45: '52260847377960000139550010001134171584734398 | U45: 2026-08-26 00:00:00.000 -0300
A46: 269308 | B46: 3. Sem nota fiscal | C46: UBR9A97 | D46: GRITSCH - POA | E46: 2026-08-11 15:33:34.000 -0300 | F46: 25053621 | G46: SIM REDE - URUGUAIANA BR 290 0152-94 - CENTRO RS | H46: 7473735015294 | J46: COMBUSTÍVEL | K46: 268.65 | L46: PENDENTE DE NOTA | U46: 2026-08-26 00:00:00.000 -0300
A47: 269308 | B47: 1. Com nota fiscal recolhida | C47: RHS8D41 | D47: GRITSCH - CWB (BASE) | E47: 2026-08-11 15:25:17.000 -0300 | F47: 25053293 | G47: POSTO JOINVILLE - GRUPO GISA | H47: 1975878000105 | I47: 9576274000106 | J47: COMBUSTÍVEL | K47: 250.31 | L47: NFE VINCULADA | M47: 2544 | N47: 2026-08-10 21:00:00.000 -0300 | O47: 250.31 | P47: '41260801975878000105550100000025441785364390 | U47: 2026-08-26 00:00:00.000 -0300
A48: 269308 | B48: 1. Com nota fiscal recolhida | C48: SFL1E46 | D48: GRITSCH - PMW | E48: 2026-08-11 15:23:18.000 -0300 | F48: 25053265 | G48: RODOPOSTO | H48: 4219621000111 | I48: 90739624000118 | J48: COMBUSTÍVEL | K48: 298.18 | L48: NFE VINCULADA | M48: 99279 | N48: 2026-08-11 21:00:00.000 -0300 | O48: 298.18 | P48: '17260804219621000111550010000992791349733063 | U48: 2026-08-26 00:00:00.000 -0300
A49: 269308 | B49: 3. Sem nota fiscal | C49: TAV9E95 | D49: GRITSCH - PET | E49: 2026-08-11 15:21:18.000 -0300 | F49: 25053242 | G49: SIM REDE - PELOTAS CAVADA 0060-31 - CENTRO RS | H49: 7473735006031 | J49: ARLA | K49: 42.42 | L49: PENDENTE DE NOTA | U49: 2026-08-26 00:00:00.000 -0300
A50: 269308 | B50: 1. Com nota fiscal recolhida | C50: UBA9H34 | D50: GRITSCH - RDN | E50: 2026-08-11 15:19:57.000 -0300 | F50: 25053230 | G50: REDE MARAJO BOM JARDIM DE GOIAS | H50: 58446194000133 | I50: 90739624001947 | J50: COMBUSTÍVEL | K50: 501.43 | L50: NFE VINCULADA | M50: 53347 | N50: 2026-08-10 21:00:00.000 -0300 | O50: 501.43 | P50: '52260858446194000133550540000533471818139992 | U50: 2026-08-26 00:00:00.000 -0300
A51: 269308 | B51: 3. Sem nota fiscal | C51: TAV9E95 | D51: GRITSCH - PET | E51: 2026-08-11 15:19:12.000 -0300 | F51: 25053221 | G51: SIM REDE - PELOTAS CAVADA 0060-31 - CENTRO RS | H51: 7473735006031 | J51: COMBUSTÍVEL | K51: 610.96 | L51: PENDENTE DE NOTA | U51: 2026-08-26 00:00:00.000 -0300
A52: 269308 | B52: 1. Com nota fiscal recolhida | C52: SEL0E76 | D52: GRITSCH - RDN | E52: 2026-08-11 15:19:08.000 -0300 | F52: 25053220 | G52: POSTO CPN - BR | H52: 23891404000118 | I52: 90739624001866 | J52: ARLA | K52: 48.25 | L52: NFE VINCULADA | M52: 131912 | N52: 2026-08-10 21:00:00.000 -0300 | O52: 48.25 | P52: '51260823891404000118550110001319121621930536 | U52: 2026-08-26 00:00:00.000 -0300
A53: 269308 | B53: 1. Com nota fiscal recolhida | C53: SEL0E76 | D53: GRITSCH - RDN | E53: 2026-08-11 15:17:45.000 -0300 | F53: 25053155 | G53: POSTO CPN - BR | H53: 23891404000118 | I53: 90739624001866 | J53: COMBUSTÍVEL | K53: 403.27 | L53: NFE VINCULADA | M53: 131911 | N53: 2026-08-10 21:00:00.000 -0300 | O53: 403.27 | P53: '51260823891404000118550110001319111895139898 | U53: 2026-08-26 00:00:00.000 -0300
A54: 269308 | B54: 1. Com nota fiscal recolhida | C54: TAZ4A48 | D54: GRITSCH - CSC | E54: 2026-08-11 15:16:55.000 -0300 | F54: 25053095 | G54: POSTO NOVO FOXX - REDE ESTRADA | H54: 2763612000161 | I54: 90739624003133 | J54: COMBUSTÍVEL | K54: 233.90 | L54: NFE VINCULADA | M54: 163210 | N54: 2026-08-10 21:00:00.000 -0300 | O54: 233.90 | P54: '41260802763612000161550020001632101317347268 | U54: 2026-08-26 00:00:00.000 -0300
A55: 269308 | B55: 1. Com nota fiscal recolhida | C55: SFM3H40 | D55: GRITSCH - CWB (BASE) | E55: 2026-08-11 15:06:58.000 -0300 | F55: 25052856 | G55: POSTO BARAO MATRIZ|| REDE BARAO | H55: 75176859000155 | I55: 9576274000106 | J55: COMBUSTÍVEL | K55: 244.80 | L55: NFE VINCULADA | M55: 389606 | N55: 2026-08-10 21:00:00.000 -0300 | O55: 244.80 | P55: '41260875176859000155550020003896061768635314 | U55: 2026-08-26 00:00:00.000 -0300
A56: 269308 | B56: 1. Com nota fiscal recolhida | C56: TAI4J01 | D56: GRITSCH - JOI | E56: 2026-08-11 14:44:25.000 -0300 | F56: 25051437 | G56: POSTO ZANDONA 7 | H56: 84711084000161 | I56: 90739624001432 | J56: COMBUSTÍVEL | K56: 273.03 | L56: NFE VINCULADA | M56: 119563 | N56: 2026-08-10 21:00:00.000 -0300 | O56: 273.03 | P56: '42260884711084000161550030001195631111744337 | U56: 2026-08-26 00:00:00.000 -0300
A57: 269308 | B57: 3. Sem nota fiscal | C57: RHS8D32 | D57: GRITSCH - CGB | E57: 2026-08-11 14:40:28.000 -0300 | F57: 25051004 | G57: AMAZONIA - 24 | H57: 9001879002619 | J57: COMBUSTÍVEL | K57: 95.08 | L57: PENDENTE DE NOTA | U57: 2026-08-26 00:00:00.000 -0300
A58: 269308 | B58: 1. Com nota fiscal recolhida | C58: TAW7H31 | D58: GRITSCH - LDB | E58: 2026-08-11 14:29:03.000 -0300 | F58: 25050039 | G58: AUTO POSTO BARUK | H58: 33286065000102 | I58: 9576274000106 | J58: ARLA | K58: 36.84 | L58: NFE VINCULADA | M58: 4450 | N58: 2026-08-10 21:00:00.000 -0300 | O58: 36.84 | P58: '41260833286065000102550100000044501014216827 | U58: 2026-08-26 00:00:00.000 -0300
A59: 269308 | B59: 1. Com nota fiscal recolhida | C59: SEL2B40 | D59: GRITSCH - PGR | E59: 2026-08-11 14:28:45.000 -0300 | F59: 25050026 | G59: POSTO ZAPA MARIUCA | REDE PRIMOS | H59: 27933025000102 | I59: 9576274000106 | J59: COMBUSTÍVEL | K59: 458.95 | L59: NFE VINCULADA | M59: 1150 | N59: 2026-08-13 21:00:00.000 -0300 | O59: 458.95 | P59: '41260827933025000102550090000011501000267280 | U59: 2026-08-26 00:00:00.000 -0300
A60: 269308 | B60: 1. Com nota fiscal recolhida | C60: TAW7H31 | D60: GRITSCH - LDB | E60: 2026-08-11 14:28:03.000 -0300 | F60: 25049964 | G60: AUTO POSTO BARUK | H60: 33286065000102 | I60: 9576274000106 | J60: COMBUSTÍVEL | K60: 758.53 | L60: NFE VINCULADA | M60: 4449 | N60: 2026-08-10 21:00:00.000 -0300 | O60: 758.53 | P60: '41260833286065000102550100000044491014216800 | U60: 2026-08-26 00:00:00.000 -0300
A61: 269308 | B61: 1. Com nota fiscal recolhida | C61: SFN1H25 | D61: GRITSCH - SNO | E61: 2026-08-11 14:27:09.000 -0300 | F61: 25049882 | G61: AUTO POSTO NOVO CEU | H61: 26602128000119 | I61: 90739624001866 | J61: COMBUSTÍVEL | K61: 142.63 | L61: NFE VINCULADA | M61: 136247 | N61: 2026-08-10 21:00:00.000 -0300 | O61: 142.63 | P61: '51260826602128000119550010001362471001773245 | U61: 2026-08-26 00:00:00.000 -0300
A62: 269308 | B62: 3. Sem nota fiscal | C62: UBD6I31 | D62: GRITSCH - CXJ | E62: 2026-08-11 14:26:45.000 -0300 | F62: 25049849 | G62: SIM REDE - CAXIAS DO SUL 0123-50 - METROPOLITANA / SERRA | H62: 7473735012350 | J62: COMBUSTÍVEL | K62: 377.78 | L62: PENDENTE DE NOTA | U62: 2026-08-26 00:00:00.000 -0300
A63: 269308 | B63: 1. Com nota fiscal recolhida | C63: SEZ3A79 | D63: GRITSCH - CTB | E63: 2026-08-11 14:22:55.000 -0300 | F63: 25049390 | G63: POSTO CAPITAL | H63: 82156977000248 | I63: 90739624001432 | J63: COMBUSTÍVEL | K63: 243.90 | L63: NFE VINCULADA | M63: 168705 | N63: 2026-08-10 21:00:00.000 -0300 | O63: 243.90 | P63: '42260882156977000248550010001687051986882038 | U63: 2026-08-26 00:00:00.000 -0300
A64: 269308 | B64: 1. Com nota fiscal recolhida | C64: RHQ6I66 | D64: GRITSCH - MGA | E64: 2026-08-11 14:22:01.000 -0300 | F64: 25049333 | G64: POSTO UNIDO | H64: 79130647000198 | I64: 9576274000106 | J64: COMBUSTÍVEL | K64: 383.75 | L64: NFE VINCULADA | M64: 16856 | N64: 2026-08-10 21:00:00.000 -0300 | O64: 383.75 | P64: '41260879130647000198550050000168561015904426 | U64: 2026-08-26 00:00:00.000 -0300
A65: 269308 | B65: 1. Com nota fiscal recolhida | C65: RHQ6I69 | D65: GRITSCH - MGA | E65: 2026-08-11 14:21:17.000 -0300 | F65: 25049271 | G65: POSTO UNIDO | H65: 79130647000198 | I65: 9576274000106 | J65: COMBUSTÍVEL | K65: 61.14 | L65: NFE VINCULADA | M65: 3023 | N65: 2026-08-10 21:00:00.000 -0300 | O65: 61.14 | P65: '41260879130647000198550070000030231015904419 | U65: 2026-08-26 00:00:00.000 -0300
A66: 269308 | B66: 1. Com nota fiscal recolhida | C66: SEN1C56 | D66: GRITSCH - GOI | E66: 2026-08-11 14:20:20.000 -0300 | F66: 25049229 | G66: POSTO 10 GOIANIA | REDE CARRETEIRO | H66: 1272434001002 | I66: 90739624001947 | J66: COMBUSTÍVEL | K66: 135.67 | L66: NFE VINCULADA | M66: 81431 | N66: 2026-08-10 21:00:00.000 -0300 | O66: 135.67 | P66: '52260801272434001002550020000814311472286075 | U66: 2026-08-26 00:00:00.000 -0300
A67: 269308 | B67: 1. Com nota fiscal recolhida | C67: RHS3G80 | D67: GRITSCH - MGA | E67: 2026-08-11 14:19:14.000 -0300 | F67: 25049113 | G67: POSTO UNIDO | H67: 79130647000198 | I67: 9576274000106 | J67: COMBUSTÍVEL | K67: 440.15 | L67: NFE VINCULADA | M67: 16855 | N67: 2026-08-10 21:00:00.000 -0300 | O67: 440.15 | P67: '41260879130647000198550050000168551015904402 | U67: 2026-08-26 00:00:00.000 -0300
A68: 269308 | B68: 1. Com nota fiscal recolhida | C68: SFI8F38 | D68: GRITSCH - MGA | E68: 2026-08-11 14:15:16.000 -0300 | F68: 25048768 | G68: COCAMAR - MARINGA | REDE COCAMAR MARINGA - PR | H68: 30429333000282 | I68: 9576274000106 | J68: COMBUSTÍVEL | K68: 295.58 | L68: NFE VINCULADA | M68: 41254 | N68: 2026-08-10 21:00:00.000 -0300 | O68: 295.58 | P68: '41260830429333000282550110000412541005182783 | U68: 2026-08-26 00:00:00.000 -0300
A69: 269308 | B69: 1. Com nota fiscal recolhida | C69: UBR9B24 | D69: GRITSCH - LDB | E69: 2026-08-11 14:10:35.000 -0300 | F69: 25048468 | G69: AUTO POSTO AMARANTE | H69: 5291412000141 | I69: 9576274000106 | J69: COMBUSTÍVEL | K69: 392.88 | L69: NFE VINCULADA | M69: 20903 | N69: 2026-08-10 21:00:00.000 -0300 | O69: 392.88 | P69: '41260805291412000141550020000209031018184815 | U69: 2026-08-26 00:00:00.000 -0300
A70: 269308 | B70: 1. Com nota fiscal recolhida | C70: UAV5J69 | D70: GRITSCH - RDN | E70: 2026-08-11 14:09:41.000 -0300 | F70: 25048434 | G70: POSTO TIGRAO - CONFRESA - GRUPO TIGRAO | H70: 3623054000282 | I70: 90739624001866 | J70: COMBUSTÍVEL | K70: 473.75 | L70: NFE VINCULADA | M70: 3383325 | N70: 2026-08-10 21:00:00.000 -0300 | O70: 473.75 | P70: '51260803623054000282550010033833251013436995 | U70: 2026-08-26 00:00:00.000 -0300
A71: 269308 | B71: 1. Com nota fiscal recolhida | C71: TBE5I64 | D71: GRITSCH - GOI | E71: 2026-08-11 14:03:09.000 -0300 | F71: 25047882 | G71: POSTO 10 GOIANIA | REDE CARRETEIRO | H71: 1272434001002 | I71: 90739624001947 | J71: COMBUSTÍVEL | K71: 291.87 | L71: NFE VINCULADA | M71: 81429 | N71: 2026-08-10 21:00:00.000 -0300 | O71: 291.87 | P71: '52260801272434001002550020000814291705266782 | U71: 2026-08-26 00:00:00.000 -0300
A72: 269308 | B72: 1. Com nota fiscal recolhida | C72: SDR8E10 | D72: GRITSCH - PGR | E72: 2026-08-11 14:02:55.000 -0300 | F72: 25047875 | G72: POSTO ZAPA MARIUCA | REDE PRIMOS | H72: 27933025000102 | I72: 9576274000106 | J72: COMBUSTÍVEL | K72: 214.09 | L72: NFE VINCULADA | M72: 1149 | N72: 2026-08-13 21:00:00.000 -0300 | O72: 214.09 | P72: '41260827933025000102550090000011491000267271 | U72: 2026-08-26 00:00:00.000 -0300
A73: 269308 | B73: 1. Com nota fiscal recolhida | C73: UBR9B25 | D73: GRITSCH - CHA | E73: 2026-08-11 13:59:42.000 -0300 | F73: 25047830 | G73: POSTO NATAL - MAXSUL | H73: 20630766000167 | I73: 90739624001432 | J73: COMBUSTÍVEL | K73: 269.16 | L73: NFE VINCULADA | M73: 59392 | N73: 2026-08-10 21:00:00.000 -0300 | O73: 269.16 | P73: '42260820630766000167550040000593921808428894 | U73: 2026-08-26 00:00:00.000 -0300
A74: 269308 | B74: 1. Com nota fiscal recolhida | C74: TBE5I66 | D74: GRITSCH - GOI | E74: 2026-08-11 13:53:38.000 -0300 | F74: 25047120 | G74: POSTO SAO JUDAS TADEU - REDE Z+Z (RODOVIA) | H74: 13759928000104 | I74: 90739624001947 | J74: COMBUSTÍVEL | K74: 230.17 | L74: NFE VINCULADA | M74: 27326 | N74: 2026-08-10 21:00:00.000 -0300 | O74: 230.17 | P74: '52260813759928000104550040000273261005194696 | U74: 2026-08-26 00:00:00.000 -0300
... A90: 269308 | B90: 1. Com nota fiscal recolhida | C90: SEP6E17 | D90: GRITSCH - PGR | E90: 2026-08-11 13:09:44.000 -0300 | F90: 25045445 | G90: POSTO ZAPA MARIUCA | REDE PRIMOS | H90: 27933025000102 | I90: 9576274000106 | J90: COMBUSTÍVEL | K90: 41.03 | L90: NFE VINCULADA | M90: 1146 | N90: 2026-08-13 21:00:00.000 -0300 | O90: 41.03 | P90: '41260827933025000102550090000011461000267237 | U90: 2026-08-26 00:00:00.000 -0300
A91: 269308 | B91: 3. Sem nota fiscal | C91: SDU9F54 | D91: GRITSCH - CXJ | E91: 2026-08-11 13:08:46.000 -0300 | F91: 25045427 | G91: SIM REDE - CAXIAS FESTA DA UVA 0015-87 - METROPOLITANA / SERRA | H91: 7473735001587 | J91: COMBUSTÍVEL | K91: 126.76 | L91: PENDENTE DE NOTA | U91: 2026-08-26 00:00:00.000 -0300
A92: 269308 | B92: 1. Com nota fiscal recolhida | C92: UBK4B57 | D92: GRITSCH - PBC | E92: 2026-08-11 13:02:08.000 -0300 | F92: 25045243 | G92: GP POSTOS - POSTO TREVO | H92: 79964177000168 | I92: 9576274000106 | J92: COMBUSTÍVEL | K92: 283.05 | L92: NFE VINCULADA | M92: 257424 | N92: 2026-08-10 21:00:00.000 -0300 | O92: 283.05 | P92: '41260879964177000168550020002574241015042866 | U92: 2026-08-26 00:00:00.000 -0300
A93: 269308 | B93: 1. Com nota fiscal recolhida | C93: SFD2H30 | D93: GRITSCH - BLN | E93: 2026-08-11 12:57:24.000 -0300 | F93: 25045086 | G93: POSTO ZANDONA 12 | H93: 83392050000199 | I93: 90739624001432 | J93: COMBUSTÍVEL | K93: 137.08 | L93: NFE VINCULADA | M93: 130093 | N93: 2026-08-10 21:00:00.000 -0300 | O93: 137.08 | P93: '42260883392050000199550020001300931111557301 | U93: 2026-08-26 00:00:00.000 -0300
A94: 269308 | B94: 1. Com nota fiscal recolhida | C94: RHS3G79 | D94: GRITSCH - LDB | E94: 2026-08-11 12:50:51.000 -0300 | F94: 25045007 | G94: AUTO POSTO CHEGADAO | H94: 3680814000102 | I94: 9576274000106 | J94: COMBUSTÍVEL | K94: 416.12 | L94: NFE VINCULADA | M94: 9441 | N94: 2026-08-10 21:00:00.000 -0300 | O94: 416.12 | P94: '41260803680814000102550080000094411245056450 | U94: 2026-08-26 00:00:00.000 -0300
A95: 269308 | B95: 3. Sem nota fiscal | C95: SDU9F80 | D95: GRITSCH - PGR | E95: 2026-08-11 12:43:45.000 -0300 | F95: 25044827 | G95: POSTO ZAPA MARIUCA | REDE PRIMOS | H95: 27933025000102 | J95: COMBUSTÍVEL | K95: 99.07 | L95: PENDENTE DE NOTA | U95: 2026-08-26 00:00:00.000 -0300
A96: 269308 | B96: 1. Com nota fiscal recolhida | C96: SEP6E19 | D96: GRITSCH - POA | E96: 2026-08-11 12:38:55.000 -0300 | F96: 25044744 | G96: BUFFON 30 - BANDEIRA BRANCA | H96: 93489243003050 | I96: 90739624002323 | J96: COMBUSTÍVEL | K96: 272.66 | L96: NFE VINCULADA | M96: 1667 | N96: 2026-08-10 21:00:00.000 -0300 | O96: 272.66 | P96: '43260893489243003050550040000016671561601521 | U96: 2026-08-26 00:00:00.000 -0300
A97: 269308 | B97: 1. Com nota fiscal recolhida | C97: SDU9F62 | D97: GRITSCH - MGA | E97: 2026-08-11 12:38:20.000 -0300 | F97: 25044738 | G97: COCAMAR - MARINGA | REDE COCAMAR MARINGA - PR | H97: 30429333000282 | I97: 9576274000106 | J97: COMBUSTÍVEL | K97: 176.21 | L97: NFE VINCULADA | M97: 41235 | N97: 2026-08-10 21:00:00.000 -0300 | O97: 176.21 | P97: '41260830429333000282550110000412351005181285 | U97: 2026-08-26 00:00:00.000 -0300
A98: 269308 | B98: 1. Com nota fiscal recolhida | C98: SDT4B70 | D98: GRITSCH - CGB | E98: 2026-08-11 12:37:22.000 -0300 | F98: 25044722 | G98: REDE DINO - POSTO TREVINHO | H98: 8603562000212 | I98: 90739624001866 | J98: COMBUSTÍVEL | K98: 83.80 | L98: NFE VINCULADA | M98: 54921 | N98: 2026-08-10 21:00:00.000 -0300 | O98: 83.80 | P98: '51260808603562000212550050000549211011645383 | U98: 2026-08-26 00:00:00.000 -0300
A99: 269308 | B99: 3. Sem nota fiscal | C99: UBM2C03 | D99: GRITSCH - CXJ | E99: 2026-08-11 12:32:52.000 -0300 | F99: 25044652 | G99: SIM REDE - CAXIAS FESTA DA UVA 0015-87 - METROPOLITANA / SERRA | H99: 7473735001587 | J99: COMBUSTÍVEL | K99: 271.04 | L99: PENDENTE DE NOTA | U99: 2026-08-26 00:00:00.000 -0300
A100: 269308 | B100: 3. Sem nota fiscal | C100: TAS4H12 | D100: GRITSCH - POA | E100: 2026-08-11 12:32:11.000 -0300 | F100: 25044538 | G100: SIM REDE - TORRES 0062-01 - SC SUL | H100: 7473735006201 | J100: COMBUSTÍVEL | K100: 227.45 | L100: PENDENTE DE NOTA | U100: 2026-08-26 00:00:00.000 -0300
A101: 269308 | B101: 3. Sem nota fiscal | C101: UBN9E25 | D101: GRITSCH - PET | E101: 2026-08-11 12:30:11.000 -0300 | F101: 25044500 | G101: SIM REDE - PELOTAS CAVADA 0060-31 - CENTRO RS | H101: 7473735006031 | J101: COMBUSTÍVEL | K101: 161.19 | L101: PENDENTE DE NOTA | U101: 2026-08-26 00:00:00.000 -0300
A102: 269308 | B102: 1. Com nota fiscal recolhida | C102: RHS8D20 | D102: GRITSCH - CWB (BASE) | E102: 2026-08-11 12:22:19.000 -0300 | F102: 25044312 | G102: POSTO JOINVILLE - GRUPO GISA | H102: 1975878000105 | I102: 9576274000106 | J102: COMBUSTÍVEL | K102: 253.29 | L102: NFE VINCULADA | M102: 2540 | N102: 2026-08-10 21:00:00.000 -0300 | O102: 253.29 | P102: '41260801975878000105550100000025401308530080 | U102: 2026-08-26 00:00:00.000 -0300
A103: 269308 | B103: 3. Sem nota fiscal | C103: UCB4H75 | D103: GRITSCH - POA | E103: 2026-08-11 12:18:59.000 -0300 | F103: 25044223 | G103: SIM REDE - SANTA MARIA BR 392 0151-03 - CENTRO RS | H103: 7473735015103 | J103: COMBUSTÍVEL | K103: 580.46 | L103: PENDENTE DE NOTA | U103: 2026-08-26 00:00:00.000 -0300
A104: 269308 | B104: 3. Sem nota fiscal | C104: BDU5G86 | D104: GRITSCH - CWB (BASE) | E104: 2026-08-11 12:18:33.000 -0300 | F104: 25044164 | G104: SIM REDE - CAXIAS FORQUETA 0007-77 - METROPOLITANA / SERRA | H104: 7473735000777 | J104: COMBUSTÍVEL | K104: 680.57 | L104: PENDENTE DE NOTA | U104: 2026-08-26 00:00:00.000 -0300
A105: 269308 | B105: 1. Com nota fiscal recolhida | C105: SFF9H65 | D105: GRITSCH - CGR | E105: 2026-08-11 12:14:52.000 -0300 | F105: 25044126 | G105: POSTO KATIA LOCATELLI URBANO | H105: 6294288000130 | I105: 90739624001190 | J105: COMBUSTÍVEL | K105: 403.31 | L105: NFE VINCULADA | M105: 178302 | N105: 2026-08-11 21:00:00.000 -0300 | O105: 403.31 | P105: '50260806294288000130550010001783021024159638 | U105: 2026-08-26 00:00:00.000 -0300
A106: 269308 | B106: 1. Com nota fiscal recolhida | C106: SDP5J33 | D106: GRITSCH - MGA | E106: 2026-08-11 12:14:37.000 -0300 | F106: 25044124 | G106: POSTO UNIDO | H106: 79130647000198 | I106: 9576274000106 | J106: COMBUSTÍVEL | K106: 203.20 | L106: NFE VINCULADA | M106: 16851 | N106: 2026-08-10 21:00:00.000 -0300 | O106: 203.20 | P106: '41260879130647000198550050000168511015903202 | U106: 2026-08-26 00:00:00.000 -0300
A107: 269308 | B107: 1. Com nota fiscal recolhida | C107: UBR9A93 | D107: GRITSCH - GPA | E107: 2026-08-11 12:11:27.000 -0300 | F107: 25044100 | G107: POSTO IDEAL GUAPO – FILIAL | H107: 3626094001330 | I107: 9576274000106 | J107: COMBUSTÍVEL | K107: 248.02 | L107: NFE VINCULADA | M107: 50605 | N107: 2026-08-10 21:00:00.000 -0300 | O107: 248.02 | P107: '41260803626094001330550010000506051137757428 | U107: 2026-08-26 00:00:00.000 -0300
A108: 269308 | B108: 1. Com nota fiscal recolhida | C108: SFG4I65 | D108: GRITSCH - PMW | E108: 2026-08-11 12:06:58.000 -0300 | F108: 25044038 | G108: RODOPOSTO | H108: 4219621000111 | I108: 90739624000118 | J108: COMBUSTÍVEL | K108: 280.00 | L108: NFE VINCULADA | M108: 99277 | N108: 2026-08-11 21:00:00.000 -0300 | O108: 280.00 | P108: '17260804219621000111550010000992771106878100 | U108: 2026-08-26 00:00:00.000 -0300
A109: 269308 | B109: 1. Com nota fiscal recolhida | C109: SFI4A20 | D109: GRITSCH - RVD | E109: 2026-08-11 12:01:02.000 -0300 | F109: 25043854 | G109: REDE MARAJO BOM JARDIM DE GOIAS | H109: 58446194000133 | I109: 90739624001947 | J109: COMBUSTÍVEL | K109: 270.29 | L109: NFE VINCULADA | M109: 53321 | N109: 2026-08-10 21:00:00.000 -0300 | O109: 270.29 | P109: '52260858446194000133550540000533211070871045 | U109: 2026-08-26 00:00:00.000 -0300
A110: 269308 | B110: 1. Com nota fiscal recolhida | C110: TAW3H21 | D110: GRITSCH - FLN | E110: 2026-08-11 11:50:23.000 -0300 | F110: 25043551 | G110: POSTO GALO - PRAIA DE FORA 0014-07 - REDE GALO | H110: 81326258001407 | I110: 90739624001432 | J110: COMBUSTÍVEL | K110: 426.05 | L110: NFE VINCULADA | M110: 28231 | N110: 2026-08-10 21:00:00.000 -0300 | O110: 426.05 | P110: '42260881326258001407550010000282311003184466 | U110: 2026-08-26 00:00:00.000 -0300
A111: 269308 | B111: 1. Com nota fiscal recolhida | C111: SFM3H48 | D111: GRITSCH - GPA | E111: 2026-08-11 11:46:53.000 -0300 | F111: 25043488 | G111: POSTO IDEAL GUAPO – FILIAL | H111: 3626094001330 | I111: 9576274000106 | J111: COMBUSTÍVEL | K111: 292.65 | L111: NFE VINCULADA | M111: 50604 | N111: 2026-08-10 21:00:00.000 -0300 | O111: 292.65 | P111: '41260803626094001330550010000506041917097810 | U111: 2026-08-26 00:00:00.000 -0300
A112: 269308 | B112: 1. Com nota fiscal recolhida | C112: SFD2H38 | D112: GRITSCH - RVD | E112: 2026-08-11 11:42:57.000 -0300 | F112: 25043331 | G112: AUTO POSTO MANIA | H112: 9427958000138 | I112: 90739624001947 | J112: COMBUSTÍVEL | K112: 195.15 | L112: NFE VINCULADA | M112: 97937 | N112: 2026-08-10 21:00:00.000 -0300 | O112: 195.15 | P112: '52260809427958000138550010000979371579939981 | U112: 2026-08-26 00:00:00.000 -0300
A113: 269308 | B113: 3. Sem nota fiscal | C113: SEP6E34 | D113: GRITSCH - POA | E113: 2026-08-11 11:38:28.000 -0300 | F113: 25043286 | G113: SIM REDE - SANTA MARIA BR 392 0151-03 - CENTRO RS | H113: 7473735015103 | J113: COMBUSTÍVEL | K113: 241.03 | L113: PENDENTE DE NOTA | U113: 2026-08-26 00:00:00.000 -0300
A114: 269308 | B114: 1. Com nota fiscal recolhida | C114: SEC5E64 | D114: GRITSCH - CGB | E114: 2026-08-11 11:24:44.000 -0300 | F114: 25042872 | G114: POSTO IGUACU - CACERES | H114: 54494203000100 | I114: 90739624001866 | J114: COMBUSTÍVEL | K114: 167.82 | L114: NFE VINCULADA | M114: 16046 | N114: 2026-08-17 21:00:00.000 -0300 | O114: 167.82 | P114: '51260854494203000100550000000160461003183390 | U114: 2026-08-26 00:00:00.000 -0300
A115: 269308 | B115: 1. Com nota fiscal recolhida | C115: RHZ7G20 | D115: GRITSCH - CGB | E115: 2026-08-11 11:24:39.000 -0300 | F115: 25042871 | G115: REDE DINO - POSTO TREVINHO | H115: 8603562000212 | I115: 90739624001866 | J115: COMBUSTÍVEL | K115: 112.22 | L115: NFE VINCULADA | M115: 54915 | N115: 2026-08-10 21:00:00.000 -0300 | O115: 112.22 | P115: '51260808603562000212550050000549151011644878 | U115: 2026-08-26 00:00:00.000 -0300
A116: 269308 | B116: 1. Com nota fiscal recolhida | C116: SDU9F71 | D116: GRITSCH - GPA | E116: 2026-08-11 11:23:36.000 -0300 | F116: 25042847 | G116: POSTO IDEAL GUAPO – FILIAL | H116: 3626094001330 | I116: 9576274000106 | J116: COMBUSTÍVEL | K116: 151.38 | L116: NFE VINCULADA | M116: 50603 | N116: 2026-08-10 21:00:00.000 -0300 | O116: 151.38 | P116: '41260803626094001330550010000506031018133388 | U116: 2026-08-26 00:00:00.000 -0300
A117: 269308 | B117: 3. Sem nota fiscal | C117: UBN9E26 | D117: GRITSCH - PET | E117: 2026-08-11 11:21:54.000 -0300 | F117: 25042817 | G117: SIM REDE - PELOTAS CAVADA 0060-31 - CENTRO RS | H117: 7473735006031 | J117: COMBUSTÍVEL | K117: 276.59 | L117: PENDENTE DE NOTA | U117: 2026-08-26 00:00:00.000 -0300
A118: 269308 | B118: 1. Com nota fiscal recolhida | C118: SDR4E25 | D118: GRITSCH - CGR | E118: 2026-08-11 11:21:45.000 -0300 | F118: 25042814 | G118: REDE IPE POSTOS DE SERVICOS | URBANO | H118: 30432373000100 | I118: 90739624001190 | J118: COMBUSTÍVEL | K118: 314.37 | L118: NFE VINCULADA | M118: 24732 | N118: 2026-08-10 21:00:00.000 -0300 | O118: 314.36 | P118: '50260830432373000100550030000247321003295243 | U118: 2026-08-26 00:00:00.000 -0300
A119: 269308 | B119: 1. Com nota fiscal recolhida | C119: BEB7C73 | D119: GRITSCH - CGR | E119: 2026-08-11 11:13:13.000 -0300 | F119: 25042588 | G119: POSTO KATIA LOCATELLI | MAE E FILHA | H119: 24601882000109 | I119: 90739624001190 | J119: COMBUSTÍVEL | K119: 263.62 | L119: NFE VINCULADA | M119: 91534 | N119: 2026-08-11 21:00:00.000 -0300 | O119: 263.62 | P119: '50260824601882000109550010000915341022951581 | U119: 2026-08-26 00:00:00.000 -0300
A120: 269308 | B120: 3. Sem nota fiscal | C120: UBH2J70 | D120: GRITSCH - POA | E120: 2026-08-11 11:12:56.000 -0300 | F120: 25042577 | G120: SIM REDE DE POSTOS – IGREJINHA - 0212-60 - METROPOLITANA / SERRA | H120: 7473735021260 | J120: COMBUSTÍVEL | K120: 518.25 | L120: PENDENTE DE NOTA | U120: 2026-08-26 00:00:00.000 -0300
A121: 269308 | B121: 1. Com nota fiscal recolhida | C121: TAS4H20 | D121: GRITSCH - SAO (PERUS) | E121: 2026-08-11 11:08:37.000 -0300 | F121: 25042510 | G121: POSTO UNIDO | H121: 79130647000198 | I121: 9576274000106 | J121: ARLA | K121: 22.90 | L121: NFE VINCULADA | M121: 20216 | N121: 2026-08-10 21:00:00.000 -0300 | O121: 22.90 | P121: '41260879130647000198550030000202161015902658 | U121: 2026-08-26 00:00:00.000 -0300
A122: 269308 | B122: 1. Com nota fiscal recolhida | C122: TAS4H20 | D122: GRITSCH - SAO (PERUS) | E122: 2026-08-11 11:06:36.000 -0300 | F122: 25042478 | G122: POSTO UNIDO | H122: 79130647000198 | I122: 9576274000106 | J122: COMBUSTÍVEL | K122: 193.27 | L122: NFE VINCULADA | M122: 20215 | N122: 2026-08-10 21:00:00.000 -0300 | O122: 193.27 | P122: '41260879130647000198550030000202151015902634 | U122: 2026-08-26 00:00:00.000 -0300
A123: 269308 | B123: 1. Com nota fiscal recolhida | C123: BEY4E58 | D123: GRITSCH - CWB (BASE) | E123: 2026-08-11 11:01:19.000 -0300 | F123: 25042324 | G123: POSTO JOINVILLE - GRUPO GISA | H123: 1975878000105 | I123: 9576274000106 | J123: COMBUSTÍVEL | K123: 289.85 | L123: NFE VINCULADA | M123: 2539 | N123: 2026-08-10 21:00:00.000 -0300 | O123: 289.85 | P123: '41260801975878000105550100000025391417651286 | U123: 2026-08-26 00:00:00.000 -0300
A124: 269308 | B124: 3. Sem nota fiscal | C124: UBR9A92 | D124: GRITSCH - POA | E124: 2026-08-11 11:00:44.000 -0300 | F124: 25042312 | G124: SIM REDE - SANTA MARIA BR 392 0151-03 - CENTRO RS | H124: 7473735015103 | J124: COMBUSTÍVEL | K124: 163.53 | L124: PENDENTE DE NOTA | U124: 2026-08-26 00:00:00.000 -0300
A125: 269308 | B125: 1. Com nota fiscal recolhida | C125: TBQ1G09 | D125: GRITSCH - CGR | E125: 2026-08-11 10:55:14.000 -0300 | F125: 25042020 | G125: REDE ARLEI - AUTO POSTO ARLEI DE PRESIDENTE EPITACIO | H125: 6068493000188 | I125: 90739624000380 | J125: ARLA | K125: 10.72 | L125: NFE VINCULADA | M125: 264138 | N125: 2026-08-11 21:00:00.000 -0300 | O125: 260.38 | P125: '35260806068493000188550010002641381001795307 | U125: 2026-08-26 00:00:00.000 -0300
A126: 269308 | B126: 1. Com nota fiscal recolhida | C126: TBQ1G09 | D126: GRITSCH - CGR | E126: 2026-08-11 10:54:21.000 -0300 | F126: 25042004 | G126: REDE ARLEI - AUTO POSTO ARLEI DE PRESIDENTE EPITACIO | H126: 6068493000188 | I126: 90739624000380 | J126: COMBUSTÍVEL | K126: 249.66 | L126: NFE VINCULADA | M126: 264138 | N126: 2026-08-11 21:00:00.000 -0300 | O126: 260.38 | P126: '35260806068493000188550010002641381001795307 | U126: 2026-08-26 00:00:00.000 -0300
A127: 269308 | B127: 1. Com nota fiscal recolhida | C127: SEL1F45 | D127: GRITSCH - CWB (BASE) | E127: 2026-08-11 10:53:55.000 -0300 | F127: 25041997 | G127: POSTO JOINVILLE - GRUPO GISA | H127: 1975878000105 | I127: 9576274000106 | J127: COMBUSTÍVEL | K127: 436.32 | L127: NFE VINCULADA | M127: 2538 | N127: 2026-08-10 21:00:00.000 -0300 | O127: 436.32 | P127: '41260801975878000105550100000025381760835847 | U127: 2026-08-26 00:00:00.000 -0300
A128: 269308 | B128: 3. Sem nota fiscal | C128: UBR9B27 | D128: GRITSCH - POA | E128: 2026-08-11 10:52:48.000 -0300 | F128: 25041983 | G128: SIM REDE - SANTA MARIA BR 392 0151-03 - CENTRO RS | H128: 7473735015103 | J128: COMBUSTÍVEL | K128: 172.51 | L128: PENDENTE DE NOTA | U128: 2026-08-26 00:00:00.000 -0300
A129: 269308 | B129: 1. Com nota fiscal recolhida | C129: TAI4I92 | D129: GRITSCH - SNO | E129: 2026-08-11 10:37:00.000 -0300 | F129: 25041671 | G129: POSTO JATOBAS – GRUPO GRANJA | H129: 10588554000105 | I129: 90739624003486 | J129: COMBUSTÍVEL | K129: 145.08 | L129: NFE VINCULADA | M129: 34037 | N129: 2026-08-10 21:00:00.000 -0300 | O129: 145.08 | P129: '51260810588554000105550040000340371555706528 | U129: 2026-08-26 00:00:00.000 -0300
A130: 269308 | B130: 1. Com nota fiscal recolhida | C130: TAI4I82 | D130: GRITSCH - SNO | E130: 2026-08-11 10:34:43.000 -0300 | F130: 25041638 | G130: POSTO JATOBAS – GRUPO GRANJA | H130: 10588554000105 | I130: 90739624003486 | J130: COMBUSTÍVEL | K130: 133.44 | L130: NFE VINCULADA | M130: 34038 | N130: 2026-08-10 21:00:00.000 -0300 | O130: 133.44 | P130: '51260810588554000105550040000340381422183076 | U130: 2026-08-26 00:00:00.000 -0300
A131: 269308 | B131: 1. Com nota fiscal recolhida | C131: SFL2F19 | D131: GRITSCH - CGB | E131: 2026-08-01 14:03:55.000 -0300 | F131: 25041265 | G131: POSTO SAO JOSE 1 | H131: 4903852000140 | I131: 90739624000118 | J131: COMBUSTÍVEL | K131: 285.73 | L131: NFE VINCULADA | M131: 19665 | N131: 2026-07-31 21:00:00.000 -0300 | O131: 285.73 | P131: '11260804903852000140550150000196651001746560 | U131: 2026-08-26 00:00:00.000 -0300
A132: 269308 | B132: 1. Com nota fiscal recolhida | C132: UBR9A92 | D132: GRITSCH - POA | E132: 2026-07-28 18:26:06.000 -0300 | F132: 25041211 | G132: SIM REDE - ALEGRETE - 019877 - CENTRO RS | H132: 7473735019877 | I132: 90739624002323 | J132: COMBUSTÍVEL | K132: 241.49 | L132: NFE VINCULADA | M132: 56880 | N132: 2026-07-27 21:00:00.000 -0300 | O132: 241.49 | P132: '43260707473735019877550080000568801009094180 | U132: 2026-08-26 00:00:00.000 -0300
A133: 269308 | B133: 1. Com nota fiscal recolhida | C133: SEL0E75 | D133: GRITSCH - LDB | E133: 2026-08-11 10:21:11.000 -0300 | F133: 25041206 | G133: CONTORNO NORTE COMERCIO DE COMBUSTIVEIS | H133: 37607755000169 | I133: 9576274000106 | J133: COMBUSTÍVEL | K133: 375.83 | L133: NFE VINCULADA | M133: 10649 | N133: 2026-08-10 21:00:00.000 -0300 | O133: 375.83 | P133: '41260837607755000169550110000106491003758624 | U133: 2026-08-26 00:00:00.000 -0300
A134: 269308 | B134: 1. Com nota fiscal recolhida | C134: TAI9A19 | D134: GRITSCH - GOI | E134: 2026-08-11 10:18:26.000 -0300 | F134: 25040902 | G134: AUTO POSTO TRACAJA | LBF | H134: 27098262000197 | I134: 90739624001947 | J134: COMBUSTÍVEL | K134: 88.92 | L134: NFE VINCULADA | M134: 73607 | N134: 2026-08-10 21:00:00.000 -0300 | O134: 88.92 | P134: '52260827098262000197550010000736071166630455 | U134: 2026-08-26 00:00:00.000 -0300
A135: 269308 | B135: 1. Com nota fiscal recolhida | C135: TAV9E96 | D135: GRITSCH - CWB (BASE) | E135: 2026-08-11 10:15:08.000 -0300 | F135: 25040730 | G135: GP POSTOS - POSTO SAO JOSE | H135: 79964177000591 | I135: 9576274000106 | J135: COMBUSTÍVEL | K135: 389.68 | L135: NFE VINCULADA | M135: 820768 | N135: 2026-08-10 21:00:00.000 -0300 | O135: 389.68 | P135: '41260879964177000591550020008207681011756843 | U135: 2026-08-26 00:00:00.000 -0300
A136: 269308 | B136: 1. Com nota fiscal recolhida | C136: SDU9F49 | D136: GRITSCH - CRI | E136: 2026-08-11 10:08:25.000 -0300 | F136: 25040464 | G136: POSTO CHILE | H136: 27643038000139 | I136: 90739624001432 | J136: COMBUSTÍVEL | K136: 317.52 | L136: NFE VINCULADA | M136: 61225 | N136: 2026-08-10 21:00:00.000 -0300 | O136: 317.52 | P136: '42260827643038000139550010000612251111308287 | U136: 2026-08-26 00:00:00.000 -0300
A137: 269308 | B137: 1. Com nota fiscal recolhida | C137: TBE5I62 | D137: GRITSCH - GOI | E137: 2026-08-11 10:07:04.000 -0300 | F137: 25040224 | G137: NOSSO POSTAO | H137: 2310460000141 | I137: 90739624001947 | J137: COMBUSTÍVEL | K137: 203.70 | L137: NFE VINCULADA | M137: 53849 | N137: 2026-08-10 21:00:00.000 -0300 | O137: 203.70 | P137: '52260802310460000141550010000538491636306125 | U137: 2026-08-26 00:00:00.000 -0300
A138: 269308 | B138: 1. Com nota fiscal recolhida | C138: TAW3H22 | D138: GRITSCH - CTB | E138: 2026-08-11 10:02:28.000 -0300 | F138: 25039496 | G138: POSTO CAPITAL | H138: 82156977000248 | I138: 90739624001432 | J138: COMBUSTÍVEL | K138: 281.56 | L138: NFE VINCULADA | M138: 168663 | N138: 2026-08-10 21:00:00.000 -0300 | O138: 281.56 | P138: '42260882156977000248550010001686631373089986 | U138: 2026-08-26 00:00:00.000 -0300
A139: 269308 | B139: 1. Com nota fiscal recolhida | C139: SFL2F19 | D139: GRITSCH - CGB | E139: 2026-08-11 09:19:14.000 -0300 | F139: 25035477 | G139: POSTO JK - COMODORO | REDE AMERICA | H139: 22611652000103 | I139: 90739624001866 | J139: COMBUSTÍVEL | K139: 169.40 | L139: NFE VINCULADA | M139: 171928 | N139: 2026-08-10 21:00:00.000 -0300 | O139: 169.40 | P139: '51260822611652000103550010001719281020395194 | U139: 2026-08-26 00:00:00.000 -0300
A140: 269308 | B140: 1. Com nota fiscal recolhida | C140: UBW4G97 | D140: GRITSCH - GOI | E140: 2026-08-11 09:17:03.000 -0300 | F140: 25035345 | G140: AUTO POSTO BRASILIA 2 | H140: 2162964000161 | I140: 90739624001947 | J140: COMBUSTÍVEL | K140: 233.85 | L140: NFE VINCULADA | M140: 67862 | N140: 2026-08-10 21:00:00.000 -0300 | O140: 233.85 | P140: '52260802162964000161550020000678621114889560 | U140: 2026-08-26 00:00:00.000 -0300
...

Sheet Rateio por Garagem
A1: Garagem | B1: COLETADO | E1: NÃO COLETADO
B2: Coletado c/ NF | C2: Estornos (Crédito) | D2: Total Coletado Líquido | E2: Ab. Cancelado | F2: Sem NF | G2: Total Não Coletado | H2: Total Geral | I2: % do Total
A3: GRITSCH - BLN | B3: =SUMIFS(Contabilidade!$M:$M,Contabilidade!$B:$B,A3,Contabilidade!$X:$X,"1. Com nota fiscal recolhida") -> 18543.19 | C3: =SUMIFS(Contabilidade!$M:$M,Contabilidade!$B:$B,A3,Contabilidade!$X:$X,"4. Crédito de estorno (desconto)") -> 0 | D3: =B3+C3 -> 18543.19 | E3: =SUMIFS(Contabilidade!$M:$M,Contabilidade!$B:$B,A3,Contabilidade!$X:$X,"2. Abastecimento cancelado (sem nota)") -> 0 | F3: =SUMIFS(Contabilidade!$M:$M,Contabilidade!$B:$B,A3,Contabilidade!$X:$X,"3. Sem nota fiscal") -> 185.25 | G3: =E3+F3 -> 185.25 | H3: =D3+G3 -> 18728.44 | I3: =IF(H$32<>0,H3/H$32,0) -> 0.042259497
A4: GRITSCH - BSB | B4: =SUMIFS(Contabilidade!$M:$M,Contabilidade!$B:$B,A4,Contabilidade!$X:$X,"1. Com nota fiscal recolhida") -> 6122.22 | C4: =SUMIFS(Contabilidade!$M:$M,Contabilidade!$B:$B,A4,Contabilidade!$X:$X,"4. Crédito de estorno (desconto)") -> 0 | D4: =B4+C4 -> 6122.22 | E4: =SUMIFS(Contabilidade!$M:$M,Contabilidade!$B:$B,A4,Contabilidade!$X:$X,"2. Abastecimento cancelado (sem nota)") -> 0 | F4: =SUMIFS(Contabilidade!$M:$M,Contabilidade!$B:$B,A4,Contabilidade!$X:$X,"3. Sem nota fiscal") -> 268.52 | G4: =E4+F4 -> 268.52 | H4: =D4+G4 -> 6390.74 | I4: =IF(H$32<>0,H4/H$32,0) -> 0.014420286
A5: GRITSCH - CGB | B5: =SUMIFS(Contabilidade!$M:$M,Contabilidade!$B:$B,A5,Contabilidade!$X:$X,"1. Com nota fiscal recolhida") -> 9370.68 | C5: =SUMIFS(Contabilidade!$M:$M,Contabilidade!$B:$B,A5,Contabilidade!$X:$X,"4. Crédito de estorno (desconto)") -> -285.67 | D5: =B5+C5 -> 9085.01 | E5: =SUMIFS(Contabilidade!$M:$M,Contabilidade!$B:$B,A5,Contabilidade!$X:$X,"2. Abastecimento cancelado (sem nota)") -> 0 | F5: =SUMIFS(Contabilidade!$M:$M,Contabilidade!$B:$B,A5,Contabilidade!$X:$X,"3. Sem nota fiscal") -> 766.29 | G5: =E5+F5 -> 766.29 | H5: =D5+G5 -> 9851.3 | I5: =IF(H$32<>0,H5/H$32,0) -> 0.022228813
A6: GRITSCH - CGR | B6: =SUMIFS(Contabilidade!$M:$M,Contabilidade!$B:$B,A6,Contabilidade!$X:$X,"1. Com nota fiscal recolhida") -> 11931.65 | C6: =SUMIFS(Contabilidade!$M:$M,Contabilidade!$B:$B,A6,Contabilidade!$X:$X,"4. Crédito de estorno (desconto)") -> 0 | D6: =B6+C6 -> 11931.65 | E6: =SUMIFS(Contabilidade!$M:$M,Contabilidade!$B:$B,A6,Contabilidade!$X:$X,"2. Abastecimento cancelado (sem nota)") -> 0 | F6: =SUMIFS(Contabilidade!$M:$M,Contabilidade!$B:$B,A6,Contabilidade!$X:$X,"3. Sem nota fiscal") -> 2027 | G6: =E6+F6 -> 2027 | H6: =D6+G6 -> 13958.65 | I6: =IF(H$32<>0,H6/H$32,0) -> 0.031496778
A7: GRITSCH - CHA | B7: =SUMIFS(Contabilidade!$M:$M,Contabilidade!$B:$B,A7,Contabilidade!$X:$X,"1. Com nota fiscal recolhida") -> 16597.92 | C7: =SUMIFS(Contabilidade!$M:$M,Contabilidade!$B:$B,A7,Contabilidade!$X:$X,"4. Crédito de estorno (desconto)") -> 0 | D7: =B7+C7 -> 16597.92 | E7: =SUMIFS(Contabilidade!$M:$M,Contabilidade!$B:$B,A7,Contabilidade!$X:$X,"2. Abastecimento cancelado (sem nota)") -> 0 | F7: =SUMIFS(Contabilidade!$M:$M,Contabilidade!$B:$B,A7,Contabilidade!$X:$X,"3. Sem nota fiscal") -> 0 | G7: =E7+F7 -> 0 | H7: =D7+G7 -> 16597.92 | I7: =IF(H$32<>0,H7/H$32,0) -> 0.037452118
A8: GRITSCH - CRI | B8: =SUMIFS(Contabilidade!$M:$M,Contabilidade!$B:$B,A8,Contabilidade!$X:$X,"1. Com nota fiscal recolhida") -> 6880.57 | C8: =SUMIFS(Contabilidade!$M:$M,Contabilidade!$B:$B,A8,Contabilidade!$X:$X,"4. Crédito de estorno (desconto)") -> 0 | D8: =B8+C8 -> 6880.57 | E8: =SUMIFS(Contabilidade!$M:$M,Contabilidade!$B:$B,A8,Contabilidade!$X:$X,"2. Abastecimento cancelado (sem nota)") -> 0 | F8: =SUMIFS(Contabilidade!$M:$M,Contabilidade!$B:$B,A8,Contabilidade!$X:$X,"3. Sem nota fiscal") -> 221.24 | G8: =E8+F8 -> 221.24 | H8: =D8+G8 -> 7101.81 | I8: =IF(H$32<>0,H8/H$32,0) -> 0.016024769
A9: GRITSCH - CSC | B9: =SUMIFS(Contabilidade!$M:$M,Contabilidade!$B:$B,A9,Contabilidade!$X:$X,"1. Com nota fiscal recolhida") -> 13041.49 | C9: =SUMIFS(Contabilidade!$M:$M,Contabilidade!$B:$B,A9,Contabilidade!$X:$X,"4. Crédito de estorno (desconto)") -> 0 | D9: =B9+C9 -> 13041.49 | E9: =SUMIFS(Contabilidade!$M:$M,Contabilidade!$B:$B,A9,Contabilidade!$X:$X,"2. Abastecimento cancelado (sem nota)") -> 0 | F9: =SUMIFS(Contabilidade!$M:$M,Contabilidade!$B:$B,A9,Contabilidade!$X:$X,"3. Sem nota fiscal") -> 0 | G9: =E9+F9 -> 0 | H9: =D9+G9 -> 13041.49 | I9: =IF(H$32<>0,H9/H$32,0) -> 0.029427267
A10: GRITSCH - CTB | B10: =SUMIFS(Contabilidade!$M:$M,Contabilidade!$B:$B,A10,Contabilidade!$X:$X,"1. Com nota fiscal recolhida") -> 14854.96 | C10: =SUMIFS(Contabilidade!$M:$M,Contabilidade!$B:$B,A10,Contabilidade!$X:$X,"4. Crédito de estorno (desconto)") -> 0 | D10: =B10+C10 -> 14854.96 | E10: =SUMIFS(Contabilidade!$M:$M,Contabilidade!$B:$B,A10,Contabilidade!$X:$X,"2. Abastecimento cancelado (sem nota)") -> 0 | F10: =SUMIFS(Contabilidade!$M:$M,Contabilidade!$B:$B,A10,Contabilidade!$X:$X,"3. Sem nota fiscal") -> 0 | G10: =E10+F10 -> 0 | H10: =D10+G10 -> 14854.96 | I10: =IF(H$32<>0,H10/H$32,0) -> 0.033519243
A11: GRITSCH - CWB (BASE) | B11: =SUMIFS(Contabilidade!$M:$M,Contabilidade!$B:$B,A11,Contabilidade!$X:$X,"1. Com nota fiscal recolhida") -> 105145.34 | C11: =SUMIFS(Contabilidade!$M:$M,Contabilidade!$B:$B,A11,Contabilidade!$X:$X,"4. Crédito de estorno (desconto)") -> 0 | D11: =B11+C11 -> 105145.34 | E11: =SUMIFS(Contabilidade!$M:$M,Contabilidade!$B:$B,A11,Contabilidade!$X:$X,"2. Abastecimento cancelado (sem nota)") -> 0 | F11: =SUMIFS(Contabilidade!$M:$M,Contabilidade!$B:$B,A11,Contabilidade!$X:$X,"3. Sem nota fiscal") -> 1349.28 | G11: =E11+F11 -> 1349.28 | H11: =D11+G11 -> 106494.62 | I11: =IF(H$32<>0,H11/H$32,0) -> 0.24029813
A12: GRITSCH - CWB (DIR) | B12: =SUMIFS(Contabilidade!$M:$M,Contabilidade!$B:$B,A12,Contabilidade!$X:$X,"1. Com nota fiscal recolhida") -> 663.33 | C12: =SUMIFS(Contabilidade!$M:$M,Contabilidade!$B:$B,A12,Contabilidade!$X:$X,"4. Crédito de estorno (desconto)") -> 0 | D12: =B12+C12 -> 663.33 | E12: =SUMIFS(Contabilidade!$M:$M,Contabilidade!$B:$B,A12,Contabilidade!$X:$X,"2. Abastecimento cancelado (sem nota)") -> 0 | F12: =SUMIFS(Contabilidade!$M:$M,Contabilidade!$B:$B,A12,Contabilidade!$X:$X,"3. Sem nota fiscal") -> 0 | G12: =E12+F12 -> 0 | H12: =D12+G12 -> 663.33 | I12: =IF(H$32<>0,H12/H$32,0) -> 0.0014967607
A13: GRITSCH - CXJ | B13: =SUMIFS(Contabilidade!$M:$M,Contabilidade!$B:$B,A13,Contabilidade!$X:$X,"1. Com nota fiscal recolhida") -> 3069.99 | C13: =SUMIFS(Contabilidade!$M:$M,Contabilidade!$B:$B,A13,Contabilidade!$X:$X,"4. Crédito de estorno (desconto)") -> 0 | D13: =B13+C13 -> 3069.99 | E13: =SUMIFS(Contabilidade!$M:$M,Contabilidade!$B:$B,A13,Contabilidade!$X:$X,"2. Abastecimento cancelado (sem nota)") -> 0 | F13: =SUMIFS(Contabilidade!$M:$M,Contabilidade!$B:$B,A13,Contabilidade!$X:$X,"3. Sem nota fiscal") -> 3868.99 | G13: =E13+F13 -> 3868.99 | H13: =D13+G13 -> 6938.98 | I13: =IF(H$32<>0,H13/H$32,0) -> 0.015657353
A14: GRITSCH - FLN | B14: =SUMIFS(Contabilidade!$M:$M,Contabilidade!$B:$B,A14,Contabilidade!$X:$X,"1. Com nota fiscal recolhida") -> 25659.95 | C14: =SUMIFS(Contabilidade!$M:$M,Contabilidade!$B:$B,A14,Contabilidade!$X:$X,"4. Crédito de estorno (desconto)") -> 0 | D14: =B14+C14 -> 25659.95 | E14: =SUMIFS(Contabilidade!$M:$M,Contabilidade!$B:$B,A14,Contabilidade!$X:$X,"2. Abastecimento cancelado (sem nota)") -> 0 | F14: =SUMIFS(Contabilidade!$M:$M,Contabilidade!$B:$B,A14,Contabilidade!$X:$X,"3. Sem nota fiscal") -> 0 | G14: =E14+F14 -> 0 | H14: =D14+G14 -> 25659.95 | I14: =IF(H$32<>0,H14/H$32,0) -> 0.057899995
... A31: REFERENCIA CURITIBA | B31: =SUMIFS(Contabilidade!$M:$M,Contabilidade!$B:$B,A31,Contabilidade!$X:$X,"1. Com nota fiscal recolhida") -> 3986.55 | C31: =SUMIFS(Contabilidade!$M:$M,Contabilidade!$B:$B,A31,Contabilidade!$X:$X,"4. Crédito de estorno (desconto)") -> 0 | D31: =B31+C31 -> 3986.55 | E31: =SUMIFS(Contabilidade!$M:$M,Contabilidade!$B:$B,A31,Contabilidade!$X:$X,"2. Abastecimento cancelado (sem nota)") -> 0 | F31: =SUMIFS(Contabilidade!$M:$M,Contabilidade!$B:$B,A31,Contabilidade!$X:$X,"3. Sem nota fiscal") -> 0 | G31: =E31+F31 -> 0 | H31: =D31+G31 -> 3986.55 | I31: =IF(H$32<>0,H31/H$32,0) -> 0.0089953887
A32: TOTAL | B32: =SUM(B3:B31) -> 414653.7 | C32: =SUM(C3:C31) -> -1468.57 | D32: =SUM(D3:D31) -> 413185.13 | E32: =SUM(E3:E31) -> 331.89 | F32: =SUM(F3:F31) -> 29660.05 | G32: =SUM(G3:G31) -> 29991.94 | H32: =SUM(H3:H31) -> 443177.07 | I32: =SUM(I3:I31) -> 1

Sheet Rateio por Posto
A1: Nome do Posto | B1: CNPJ do Posto | C1: COLETADO | F1: NÃO COLETADO
C2: Coletado c/ NF | D2: Estornos (Crédito) | E2: Total Coletado Líquido | F2: Ab. Cancelado | G2: Sem NF | H2: Total Não Coletado | I2: Total Geral | J2: % do Total
A3: AMAZONIA - 24 | B3: =IFERROR(INDEX(Contabilidade!$K:$K,MATCH($A3,Contabilidade!$J:$J,0)),"") -> 9001879002619 | C3: =SUMIFS(Contabilidade!$M:$M,Contabilidade!$J:$J,$A3,Contabilidade!$X:$X,"1. Com nota fiscal recolhida") -> 0 | D3: =SUMIFS(Contabilidade!$M:$M,Contabilidade!$J:$J,$A3,Contabilidade!$X:$X,"4. Crédito de estorno (desconto)") -> 0 | E3: =C3+D3 -> 0 | F3: =SUMIFS(Contabilidade!$M:$M,Contabilidade!$J:$J,$A3,Contabilidade!$X:$X,"2. Abastecimento cancelado (sem nota)") -> 0 | G3: =SUMIFS(Contabilidade!$M:$M,Contabilidade!$J:$J,$A3,Contabilidade!$X:$X,"3. Sem nota fiscal") -> 1936.51 | H3: =F3+G3 -> 1936.51 | I3: =E3+H3 -> 1936.51 | J3: =IF(I$208,I3/I$208,0) -> 0.0043696078
A4: AUTO POSTO AMARANTE | B4: =IFERROR(INDEX(Contabilidade!$K:$K,MATCH($A4,Contabilidade!$J:$J,0)),"") -> 5291412000141 | C4: =SUMIFS(Contabilidade!$M:$M,Contabilidade!$J:$J,$A4,Contabilidade!$X:$X,"1. Com nota fiscal recolhida") -> 718.7 | D4: =SUMIFS(Contabilidade!$M:$M,Contabilidade!$J:$J,$A4,Contabilidade!$X:$X,"4. Crédito de estorno (desconto)") -> 0 | E4: =C4+D4 -> 718.7 | F4: =SUMIFS(Contabilidade!$M:$M,Contabilidade!$J:$J,$A4,Contabilidade!$X:$X,"2. Abastecimento cancelado (sem nota)") -> 0 | G4: =SUMIFS(Contabilidade!$M:$M,Contabilidade!$J:$J,$A4,Contabilidade!$X:$X,"3. Sem nota fiscal") -> 0 | H4: =F4+G4 -> 0 | I4: =E4+H4 -> 718.7 | J4: =IF(I$208,I4/I$208,0) -> 0.0016216994
A5: AUTO POSTO BANDEIRANTES - JUARA | B5: =IFERROR(INDEX(Contabilidade!$K:$K,MATCH($A5,Contabilidade!$J:$J,0)),"") -> 22620102000142 | C5: =SUMIFS(Contabilidade!$M:$M,Contabilidade!$J:$J,$A5,Contabilidade!$X:$X,"1. Com nota fiscal recolhida") -> 103.6 | D5: =SUMIFS(Contabilidade!$M:$M,Contabilidade!$J:$J,$A5,Contabilidade!$X:$X,"4. Crédito de estorno (desconto)") -> 0 | E5: =C5+D5 -> 103.6 | F5: =SUMIFS(Contabilidade!$M:$M,Contabilidade!$J:$J,$A5,Contabilidade!$X:$X,"2. Abastecimento cancelado (sem nota)") -> 0 | G5: =SUMIFS(Contabilidade!$M:$M,Contabilidade!$J:$J,$A5,Contabilidade!$X:$X,"3. Sem nota fiscal") -> 0 | H5: =F5+G5 -> 0 | I5: =E5+H5 -> 103.6 | J5: =IF(I$208,I5/I$208,0) -> 0.00023376661
A6: AUTO POSTO BARUK | B6: =IFERROR(INDEX(Contabilidade!$K:$K,MATCH($A6,Contabilidade!$J:$J,0)),"") -> 33286065000102 | C6: =SUMIFS(Contabilidade!$M:$M,Contabilidade!$J:$J,$A6,Contabilidade!$X:$X,"1. Com nota fiscal recolhida") -> 15588.05 | D6: =SUMIFS(Contabilidade!$M:$M,Contabilidade!$J:$J,$A6,Contabilidade!$X:$X,"4. Crédito de estorno (desconto)") -> 0 | E6: =C6+D6 -> 15588.05 | F6: =SUMIFS(Contabilidade!$M:$M,Contabilidade!$J:$J,$A6,Contabilidade!$X:$X,"2. Abastecimento cancelado (sem nota)") -> 0 | G6: =SUMIFS(Contabilidade!$M:$M,Contabilidade!$J:$J,$A6,Contabilidade!$X:$X,"3. Sem nota fiscal") -> 0 | H6: =F6+G6 -> 0 | I6: =E6+H6 -> 15588.05 | J6: =IF(I$208,I6/I$208,0) -> 0.035173413
A7: AUTO POSTO BATISTELLA | B7: =IFERROR(INDEX(Contabilidade!$K:$K,MATCH($A7,Contabilidade!$J:$J,0)),"") -> 44746308000156 | C7: =SUMIFS(Contabilidade!$M:$M,Contabilidade!$J:$J,$A7,Contabilidade!$X:$X,"1. Com nota fiscal recolhida") -> 668.2 | D7: =SUMIFS(Contabilidade!$M:$M,Contabilidade!$J:$J,$A7,Contabilidade!$X:$X,"4. Crédito de estorno (desconto)") -> 0 | E7: =C7+D7 -> 668.2 | F7: =SUMIFS(Contabilidade!$M:$M,Contabilidade!$J:$J,$A7,Contabilidade!$X:$X,"2. Abastecimento cancelado (sem nota)") -> 0 | G7: =SUMIFS(Contabilidade!$M:$M,Contabilidade!$J:$J,$A7,Contabilidade!$X:$X,"3. Sem nota fiscal") -> 0 | H7: =F7+G7 -> 0 | I7: =E7+H7 -> 668.2 | J7: =IF(I$208,I7/I$208,0) -> 0.0015077495
A8: AUTO POSTO BRASILIA 2 | B8: =IFERROR(INDEX(Contabilidade!$K:$K,MATCH($A8,Contabilidade!$J:$J,0)),"") -> 2162964000161 | C8: =SUMIFS(Contabilidade!$M:$M,Contabilidade!$J:$J,$A8,Contabilidade!$X:$X,"1. Com nota fiscal recolhida") -> 662.78 | D8: =SUMIFS(Contabilidade!$M:$M,Contabilidade!$J:$J,$A8,Contabilidade!$X:$X,"4. Crédito de estorno (desconto)") -> 0 | E8: =C8+D8 -> 662.78 | F8: =SUMIFS(Contabilidade!$M:$M,Contabilidade!$J:$J,$A8,Contabilidade!$X:$X,"2. Abastecimento cancelado (sem nota)") -> 0 | G8: =SUMIFS(Contabilidade!$M:$M,Contabilidade!$J:$J,$A8,Contabilidade!$X:$X,"3. Sem nota fiscal") -> 0 | H8: =F8+G8 -> 0 | I8: =E8+H8 -> 662.78 | J8: =IF(I$208,I8/I$208,0) -> 0.0014955196
A9: AUTO POSTO CHEGADAO | B9: =IFERROR(INDEX(Contabilidade!$K:$K,MATCH($A9,Contabilidade!$J:$J,0)),"") -> 3680814000102 | C9: =SUMIFS(Contabilidade!$M:$M,Contabilidade!$J:$J,$A9,Contabilidade!$X:$X,"1. Com nota fiscal recolhida") -> 1040.22 | D9: =SUMIFS(Contabilidade!$M:$M,Contabilidade!$J:$J,$A9,Contabilidade!$X:$X,"4. Crédito de estorno (desconto)") -> 0 | E9: =C9+D9 -> 1040.22 | F9: =SUMIFS(Contabilidade!$M:$M,Contabilidade!$J:$J,$A9,Contabilidade!$X:$X,"2. Abastecimento cancelado (sem nota)") -> 0 | G9: =SUMIFS(Contabilidade!$M:$M,Contabilidade!$J:$J,$A9,Contabilidade!$X:$X,"3. Sem nota fiscal") -> 0 | H9: =F9+G9 -> 0 | I9: =E9+H9 -> 1040.22 | J9: =IF(I$208,I9/I$208,0) -> 0.0023471882
A10: AUTO POSTO CIDADE - PORANGATU | B10: =IFERROR(INDEX(Contabilidade!$K:$K,MATCH($A10,Contabilidade!$J:$J,0)),"") -> 33360405000190 | C10: =SUMIFS(Contabilidade!$M:$M,Contabilidade!$J:$J,$A10,Contabilidade!$X:$X,"1. Com nota fiscal recolhida") -> 4803.69 | D10: =SUMIFS(Contabilidade!$M:$M,Contabilidade!$J:$J,$A10,Contabilidade!$X:$X,"4. Crédito de estorno (desconto)") -> 0 | E10: =C10+D10 -> 4803.69 | F10: =SUMIFS(Contabilidade!$M:$M,Contabilidade!$J:$J,$A10,Contabilidade!$X:$X,"2. Abastecimento cancelado (sem nota)") -> 0 | G10: =SUMIFS(Contabilidade!$M:$M,Contabilidade!$J:$J,$A10,Contabilidade!$X:$X,"3. Sem nota fiscal") -> 0 | H10: =F10+G10 -> 0 | I10: =E10+H10 -> 4803.69 | J10: =IF(I$208,I10/I$208,0) -> 0.010839212
A11: AUTO POSTO CIMATEL | B11: =IFERROR(INDEX(Contabilidade!$K:$K,MATCH($A11,Contabilidade!$J:$J,0)),"") -> 656619000230 | C11: =SUMIFS(Contabilidade!$M:$M,Contabilidade!$J:$J,$A11,Contabilidade!$X:$X,"1. Com nota fiscal recolhida") -> 187.94 | D11: =SUMIFS(Contabilidade!$M:$M,Contabilidade!$J:$J,$A11,Contabilidade!$X:$X,"4. Crédito de estorno (desconto)") -> 0 | E11: =C11+D11 -> 187.94 | F11: =SUMIFS(Contabilidade!$M:$M,Contabilidade!$J:$J,$A11,Contabilidade!$X:$X,"2. Abastecimento cancelado (sem nota)") -> 0 | G11: =SUMIFS(Contabilidade!$M:$M,Contabilidade!$J:$J,$A11,Contabilidade!$X:$X,"3. Sem nota fiscal") -> 0 | H11: =F11+G11 -> 0 | I11: =E11+H11 -> 187.94 | J11: =IF(I$208,I11/I$208,0) -> 0.00042407429
A12: AUTO POSTO CONFIANCA | B12: =IFERROR(INDEX(Contabilidade!$K:$K,MATCH($A12,Contabilidade!$J:$J,0)),"") -> 8810726000100 | C12: =SUMIFS(Contabilidade!$M:$M,Contabilidade!$J:$J,$A12,Contabilidade!$X:$X,"1. Com nota fiscal recolhida") -> 3837 | D12: =SUMIFS(Contabilidade!$M:$M,Contabilidade!$J:$J,$A12,Contabilidade!$X:$X,"4. Crédito de estorno (desconto)") -> 0 | E12: =C12+D12 -> 3837 | F12: =SUMIFS(Contabilidade!$M:$M,Contabilidade!$J:$J,$A12,Contabilidade!$X:$X,"2. Abastecimento cancelado (sem nota)") -> 0 | G12: =SUMIFS(Contabilidade!$M:$M,Contabilidade!$J:$J,$A12,Contabilidade!$X:$X,"3. Sem nota fiscal") -> 0 | H12: =F12+G12 -> 0 | I12: =E12+H12 -> 3837 | J12: =IF(I$208,I12/I$208,0) -> 0.0086579389
A13: AUTO POSTO DARE | B13: =IFERROR(INDEX(Contabilidade!$K:$K,MATCH($A13,Contabilidade!$J:$J,0)),"") -> 78253424000155 | C13: =SUMIFS(Contabilidade!$M:$M,Contabilidade!$J:$J,$A13,Contabilidade!$X:$X,"1. Com nota fiscal recolhida") -> 2230.34 | D13: =SUMIFS(Contabilidade!$M:$M,Contabilidade!$J:$J,$A13,Contabilidade!$X:$X,"4. Crédito de estorno (desconto)") -> 0 | E13: =C13+D13 -> 2230.34 | F13: =SUMIFS(Contabilidade!$M:$M,Contabilidade!$J:$J,$A13,Contabilidade!$X:$X,"2. Abastecimento cancelado (sem nota)") -> 0 | G13: =SUMIFS(Contabilidade!$M:$M,Contabilidade!$J:$J,$A13,Contabilidade!$X:$X,"3. Sem nota fiscal") -> 0 | H13: =F13+G13 -> 0 | I13: =E13+H13 -> 2230.34 | J13: =IF(I$208,I13/I$208,0) -> 0.005032616
A14: AUTO POSTO DUQUE CENTENARIO | B14: =IFERROR(INDEX(Contabilidade!$K:$K,MATCH($A14,Contabilidade!$J:$J,0)),"") -> 27751075017640 | C14: =SUMIFS(Contabilidade!$M:$M,Contabilidade!$J:$J,$A14,Contabilidade!$X:$X,"1. Com nota fiscal recolhida") -> 3324.71 | D14: =SUMIFS(Contabilidade!$M:$M,Contabilidade!$J:$J,$A14,Contabilidade!$X:$X,"4. Crédito de estorno (desconto)") -> 0 | E14: =C14+D14 -> 3324.71 | F14: =SUMIFS(Contabilidade!$M:$M,Contabilidade!$J:$J,$A14,Contabilidade!$X:$X,"2. Abastecimento cancelado (sem nota)") -> 0 | G14: =SUMIFS(Contabilidade!$M:$M,Contabilidade!$J:$J,$A14,Contabilidade!$X:$X,"3. Sem nota fiscal") -> 0 | H14: =F14+G14 -> 0 | I14: =E14+H14 -> 3324.71 | J14: =IF(I$208,I14/I$208,0) -> 0.0075019901
... A207: XANXERE AV. BRASIL - FILIAL 41 - REDE TRADICAO | B207: =IFERROR(INDEX(Contabilidade!$K:$K,MATCH($A207,Contabilidade!$J:$J,0)),"") -> 37435735001391 | C207: =SUMIFS(Contabilidade!$M:$M,Contabilidade!$J:$J,$A207,Contabilidade!$X:$X,"1. Com nota fiscal recolhida") -> 277.77 | D207: =SUMIFS(Contabilidade!$M:$M,Contabilidade!$J:$J,$A207,Contabilidade!$X:$X,"4. Crédito de estorno (desconto)") -> 0 | E207: =C207+D207 -> 277.77 | F207: =SUMIFS(Contabilidade!$M:$M,Contabilidade!$J:$J,$A207,Contabilidade!$X:$X,"2. Abastecimento cancelado (sem nota)") -> 0 | G207: =SUMIFS(Contabilidade!$M:$M,Contabilidade!$J:$J,$A207,Contabilidade!$X:$X,"3. Sem nota fiscal") -> 0 | H207: =F207+G207 -> 0 | I207: =E207+H207 -> 277.77 | J207: =IF(I$208,I207/I$208,0) -> 0.00062676979
A208: TOTAL | C208: =SUM(C3:C207) -> 414653.7 | D208: =SUM(D3:D207) -> -1468.57 | E208: =SUM(E3:E207) -> 413185.13 | F208: =SUM(F3:F207) -> 331.89 | G208: =SUM(G3:G207) -> 29660.05 | H208: =SUM(H3:H207) -> 29991.94 | I208: =SUM(I3:I207) -> 443177.07 | J208: =SUM(J3:J207) -> 1
